{
  "lastUpdated": "2026-04-16T12:42:16",
  "market": "Michigan",
  "systems": {
    "henryford_pc": {
      "name": "Henry Ford Primary Care",
      "locations": [
        {
          "id": "hfpc-45381",
          "name": "Henry Ford Medical Center - Plymouth with Laila Abdallah, DO.",
          "area": "Ann Arbor Rd Plymouth",
          "type": "Primary Care",
          "sameDaySlots": 0,
          "nextDaySlots": 0,
          "nextAvailable": "Wed 4/29 \u2014 28 slots (first: 8:00 AM)",
          "nextAvailableDate": "Wed 4/29",
          "source": "MyChart",
          "lastChecked": "2026-04-16T12:43:10.156346",
          "address": "40777 Ann Arbor Rd Plymouth MI 48170",
          "lat": 42.281,
          "lng": -83.749,
          "times": [],
          "zip": "40777"
        }
      ]
    },
    "gohealth_uc": {
      "name": "GoHealth / Henry Ford UC",
      "locations": [
        {
          "id": "gh-32130",
          "name": "GoHealth UC \u2014 Berkley",
          "area": "Berkley",
          "type": "Urgent Care",
          "sameDaySlots": 27,
          "nextDaySlots": 0,
          "nextAvailable": "Thu 4/16 \u2014 27 slots (first: 12:59 PM)",
          "nextAvailableDate": "Thu 4/16",
          "source": "GoHealth",
          "lastChecked": "2026-04-16T12:37:29.526173",
          "address": "2695 Coolidge Hwy, Berkley, MI 48072",
          "lat": 42.5,
          "lng": -83.184,
          "times": [
            "12:59 PM",
            "1:14 PM",
            "1:29 PM",
            "1:44 PM",
            "1:59 PM",
            "2:14 PM",
            "2:29 PM",
            "2:44 PM",
            "2:59 PM",
            "3:14 PM",
            "3:29 PM",
            "3:44 PM",
            "3:59 PM",
            "4:14 PM",
            "4:29 PM",
            "4:44 PM",
            "4:59 PM",
            "5:14 PM",
            "5:29 PM",
            "5:44 PM"
          ],
          "zip": "48072"
        },
        {
          "id": "gh-81037",
          "name": "GoHealth UC \u2014 Bruce Township",
          "area": "Bruce Township",
          "type": "Urgent Care",
          "sameDaySlots": 22,
          "nextDaySlots": 0,
          "nextAvailable": "Thu 4/16 \u2014 22 slots (first: 12:41 PM)",
          "nextAvailableDate": "Thu 4/16",
          "source": "GoHealth",
          "lastChecked": "2026-04-16T12:37:49.553484",
          "address": "71050 Van Dyke Rd, Bruce Township, MI 48065",
          "lat": 42.818,
          "lng": -83.019,
          "times": [
            "12:41 PM",
            "1:15 PM",
            "1:30 PM",
            "1:45 PM",
            "2:00 PM",
            "2:15 PM",
            "2:30 PM",
            "2:45 PM",
            "3:15 PM",
            "3:45 PM",
            "4:15 PM",
            "4:45 PM",
            "5:15 PM",
            "5:30 PM",
            "5:45 PM",
            "6:00 PM",
            "6:15 PM",
            "6:30 PM",
            "6:45 PM",
            "7:00 PM"
          ],
          "zip": "71050"
        },
        {
          "id": "gh-34401",
          "name": "GoHealth UC \u2014 Canton",
          "area": "Canton",
          "type": "Urgent Care",
          "sameDaySlots": 22,
          "nextDaySlots": 0,
          "nextAvailable": "Thu 4/16 \u2014 22 slots (first: 12:49 PM)",
          "nextAvailableDate": "Thu 4/16",
          "source": "GoHealth",
          "lastChecked": "2026-04-16T12:38:09.705089",
          "address": "43821 Ford Rd, Canton, MI 48187",
          "lat": 42.322,
          "lng": -83.475,
          "times": [
            "12:49 PM",
            "1:04 PM",
            "1:19 PM",
            "1:49 PM",
            "2:04 PM",
            "2:19 PM",
            "2:34 PM",
            "2:49 PM",
            "3:04 PM",
            "3:45 PM",
            "4:00 PM",
            "4:15 PM",
            "4:30 PM",
            "4:45 PM",
            "5:15 PM",
            "5:30 PM",
            "6:00 PM",
            "6:15 PM",
            "6:30 PM",
            "6:45 PM"
          ],
          "zip": "43821"
        },
        {
          "id": "gh-71950",
          "name": "GoHealth UC \u2014 Chesterfield",
          "area": "Chesterfield",
          "type": "Urgent Care",
          "sameDaySlots": 26,
          "nextDaySlots": 0,
          "nextAvailable": "Thu 4/16 \u2014 26 slots (first: 12:53 PM)",
          "nextAvailableDate": "Thu 4/16",
          "source": "GoHealth",
          "lastChecked": "2026-04-16T12:38:29.355734",
          "address": "50637 Gratiot Ave, Chesterfield, MI 48051",
          "lat": 42.673,
          "lng": -82.838,
          "times": [
            "12:53 PM",
            "1:08 PM",
            "1:23 PM",
            "1:38 PM",
            "1:53 PM",
            "2:08 PM",
            "2:23 PM",
            "2:38 PM",
            "2:53 PM",
            "3:08 PM",
            "3:23 PM",
            "3:38 PM",
            "3:53 PM",
            "4:08 PM",
            "4:23 PM",
            "4:38 PM",
            "4:53 PM",
            "5:08 PM",
            "5:23 PM",
            "5:38 PM"
          ],
          "zip": "50637"
        },
        {
          "id": "gh-20341",
          "name": "GoHealth UC \u2014 Clinton Township",
          "area": "Clinton Township",
          "type": "Urgent Care",
          "sameDaySlots": 17,
          "nextDaySlots": 0,
          "nextAvailable": "Thu 4/16 \u2014 17 slots (first: 12:53 PM)",
          "nextAvailableDate": "Thu 4/16",
          "source": "GoHealth",
          "lastChecked": "2026-04-16T12:38:48.992720",
          "address": "42010 Garfield Rd, Clinton Township, MI 48038",
          "lat": 42.582,
          "lng": -82.929,
          "times": [
            "12:53 PM",
            "1:35 PM",
            "2:45 PM",
            "3:00 PM",
            "3:30 PM",
            "4:00 PM",
            "4:15 PM",
            "4:45 PM",
            "5:15 PM",
            "5:30 PM",
            "5:45 PM",
            "6:00 PM",
            "6:15 PM",
            "6:30 PM",
            "7:00 PM",
            "7:15 PM",
            "7:30 PM"
          ],
          "zip": "42010"
        },
        {
          "id": "gh-68051",
          "name": "GoHealth UC \u2014 Commerce Township",
          "area": "Commerce Township",
          "type": "Urgent Care",
          "sameDaySlots": 26,
          "nextDaySlots": 0,
          "nextAvailable": "Thu 4/16 \u2014 26 slots (first: 1:09 PM)",
          "nextAvailableDate": "Thu 4/16",
          "source": "GoHealth",
          "lastChecked": "2026-04-16T12:39:09.822617",
          "address": "3030 Union Lake Rd, Commerce Township, MI 48382",
          "lat": 42.568,
          "lng": -83.494,
          "times": [
            "1:09 PM",
            "1:24 PM",
            "1:39 PM",
            "1:54 PM",
            "2:09 PM",
            "2:24 PM",
            "2:39 PM",
            "2:54 PM",
            "3:09 PM",
            "3:24 PM",
            "3:39 PM",
            "3:54 PM",
            "4:09 PM",
            "4:24 PM",
            "4:39 PM",
            "4:54 PM",
            "5:09 PM",
            "5:24 PM",
            "5:39 PM",
            "5:54 PM"
          ],
          "zip": "48382"
        },
        {
          "id": "gh-16057",
          "name": "GoHealth UC \u2014 Dearborn Heights",
          "area": "Dearborn Heights",
          "type": "Urgent Care",
          "sameDaySlots": 25,
          "nextDaySlots": 0,
          "nextAvailable": "Thu 4/16 \u2014 25 slots (first: 1:15 PM)",
          "nextAvailableDate": "Thu 4/16",
          "source": "GoHealth",
          "lastChecked": "2026-04-16T12:39:33.814628",
          "address": "25520 Ford Rd, Dearborn Heights, MI 48127",
          "lat": 42.337,
          "lng": -83.273,
          "times": [
            "1:15 PM",
            "1:30 PM",
            "1:45 PM",
            "2:00 PM",
            "2:15 PM",
            "2:30 PM",
            "2:45 PM",
            "3:00 PM",
            "3:15 PM",
            "3:30 PM",
            "3:45 PM",
            "4:00 PM",
            "4:15 PM",
            "4:30 PM",
            "4:45 PM",
            "5:15 PM",
            "5:30 PM",
            "5:45 PM",
            "6:00 PM",
            "6:15 PM"
          ],
          "zip": "25520"
        },
        {
          "id": "gh-21526",
          "name": "GoHealth UC \u2014 Fraser",
          "area": "Fraser",
          "type": "Urgent Care",
          "sameDaySlots": 22,
          "nextDaySlots": 0,
          "nextAvailable": "Thu 4/16 \u2014 22 slots (first: 1:15 PM)",
          "nextAvailableDate": "Thu 4/16",
          "source": "GoHealth",
          "lastChecked": "2026-04-16T12:39:53.736217",
          "address": "33730 Garfield Rd, Fraser, MI 48026",
          "lat": 42.539,
          "lng": -82.949,
          "times": [
            "1:15 PM",
            "1:30 PM",
            "1:45 PM",
            "2:00 PM",
            "2:15 PM",
            "2:30 PM",
            "2:45 PM",
            "3:00 PM",
            "3:15 PM",
            "3:45 PM",
            "4:00 PM",
            "4:15 PM",
            "5:15 PM",
            "5:30 PM",
            "5:45 PM",
            "6:00 PM",
            "6:15 PM",
            "6:30 PM",
            "6:45 PM",
            "7:00 PM"
          ],
          "zip": "33730"
        },
        {
          "id": "gh-12531",
          "name": "GoHealth UC \u2014 Livonia",
          "area": "Livonia",
          "type": "Urgent Care",
          "sameDaySlots": 25,
          "nextDaySlots": 0,
          "nextAvailable": "Thu 4/16 \u2014 25 slots (first: 12:55 PM)",
          "nextAvailableDate": "Thu 4/16",
          "source": "GoHealth",
          "lastChecked": "2026-04-16T12:40:13.549431",
          "address": "37672 Seven Mile Rd, Livonia, MI 48152",
          "lat": 42.4,
          "lng": -83.38,
          "times": [
            "12:55 PM",
            "1:10 PM",
            "1:25 PM",
            "1:40 PM",
            "1:55 PM",
            "2:10 PM",
            "2:51 PM",
            "3:06 PM",
            "3:21 PM",
            "3:36 PM",
            "3:51 PM",
            "4:06 PM",
            "4:21 PM",
            "4:36 PM",
            "4:51 PM",
            "5:06 PM",
            "5:21 PM",
            "5:36 PM",
            "5:51 PM",
            "6:06 PM"
          ],
          "zip": "37672"
        },
        {
          "id": "gh-74594",
          "name": "GoHealth UC \u2014 Southfield",
          "area": "Southfield",
          "type": "Urgent Care",
          "sameDaySlots": 26,
          "nextDaySlots": 0,
          "nextAvailable": "Thu 4/16 \u2014 26 slots (first: 12:49 PM)",
          "nextAvailableDate": "Thu 4/16",
          "source": "GoHealth",
          "lastChecked": "2026-04-16T12:40:34.308913",
          "address": "29305 Southfield Rd, Southfield, MI 48076",
          "lat": 42.473,
          "lng": -83.222,
          "times": [
            "12:49 PM",
            "1:04 PM",
            "1:19 PM",
            "1:34 PM",
            "1:49 PM",
            "2:04 PM",
            "2:19 PM",
            "2:34 PM",
            "3:16 PM",
            "3:31 PM",
            "3:46 PM",
            "4:01 PM",
            "4:16 PM",
            "4:31 PM",
            "4:46 PM",
            "5:01 PM",
            "5:16 PM",
            "5:31 PM",
            "5:46 PM",
            "6:01 PM"
          ],
          "zip": "29305"
        },
        {
          "id": "gh-41511",
          "name": "GoHealth UC \u2014 Southgate",
          "area": "Southgate",
          "type": "Urgent Care",
          "sameDaySlots": 23,
          "nextDaySlots": 0,
          "nextAvailable": "Thu 4/16 \u2014 23 slots (first: 1:11 PM)",
          "nextAvailableDate": "Thu 4/16",
          "source": "GoHealth",
          "lastChecked": "2026-04-16T12:40:54.956072",
          "address": "14750 Dix Toledo Rd, Southgate, MI 48195",
          "lat": 42.214,
          "lng": -83.194,
          "times": [
            "1:11 PM",
            "1:26 PM",
            "1:41 PM",
            "1:56 PM",
            "2:11 PM",
            "2:45 PM",
            "3:00 PM",
            "3:15 PM",
            "3:30 PM",
            "3:45 PM",
            "4:00 PM",
            "4:30 PM",
            "4:45 PM",
            "5:15 PM",
            "5:30 PM",
            "5:45 PM",
            "6:00 PM",
            "6:15 PM",
            "6:30 PM",
            "6:45 PM"
          ],
          "zip": "14750"
        },
        {
          "id": "gh-59381",
          "name": "GoHealth UC \u2014 St. Clair Shores",
          "area": "St. Clair Shores",
          "type": "Urgent Care",
          "sameDaySlots": 25,
          "nextDaySlots": 0,
          "nextAvailable": "Thu 4/16 \u2014 25 slots (first: 12:56 PM)",
          "nextAvailableDate": "Thu 4/16",
          "source": "GoHealth",
          "lastChecked": "2026-04-16T12:41:14.467625",
          "address": "21950 Harper Ave, St. Clair Shores, MI 48080",
          "lat": 42.497,
          "lng": -82.891,
          "times": [
            "12:56 PM",
            "1:11 PM",
            "1:26 PM",
            "1:41 PM",
            "1:56 PM",
            "2:11 PM",
            "2:26 PM",
            "2:41 PM",
            "2:56 PM",
            "3:11 PM",
            "3:26 PM",
            "3:41 PM",
            "3:56 PM",
            "4:11 PM",
            "4:26 PM",
            "4:41 PM",
            "4:56 PM",
            "5:11 PM",
            "5:26 PM",
            "5:41 PM"
          ],
          "zip": "21950"
        },
        {
          "id": "gh-31635",
          "name": "GoHealth UC \u2014 Taylor",
          "area": "Taylor",
          "type": "Urgent Care",
          "sameDaySlots": 24,
          "nextDaySlots": 0,
          "nextAvailable": "Thu 4/16 \u2014 24 slots (first: 12:56 PM)",
          "nextAvailableDate": "Thu 4/16",
          "source": "GoHealth",
          "lastChecked": "2026-04-16T12:41:34.103742",
          "address": "22395 Ecorse Rd, Taylor, MI 48180",
          "lat": 42.241,
          "lng": -83.269,
          "times": [
            "12:56 PM",
            "1:11 PM",
            "1:26 PM",
            "1:41 PM",
            "1:56 PM",
            "2:28 PM",
            "2:43 PM",
            "2:58 PM",
            "3:13 PM",
            "3:28 PM",
            "3:43 PM",
            "3:58 PM",
            "4:13 PM",
            "4:55 PM",
            "5:10 PM",
            "5:25 PM",
            "5:40 PM",
            "5:55 PM",
            "6:10 PM",
            "6:25 PM"
          ],
          "zip": "22395"
        },
        {
          "id": "gh-27302",
          "name": "GoHealth UC \u2014 West Bloomfield",
          "area": "West Bloomfield",
          "type": "Urgent Care",
          "sameDaySlots": 27,
          "nextDaySlots": 0,
          "nextAvailable": "Thu 4/16 \u2014 27 slots (first: 12:56 PM)",
          "nextAvailableDate": "Thu 4/16",
          "source": "GoHealth",
          "lastChecked": "2026-04-16T12:41:54.255990",
          "address": "6555 Orchard Lake Rd, West Bloomfield, MI 48322",
          "lat": 42.565,
          "lng": -83.382,
          "times": [
            "12:56 PM",
            "1:11 PM",
            "1:26 PM",
            "1:41 PM",
            "1:56 PM",
            "2:11 PM",
            "2:26 PM",
            "2:41 PM",
            "2:56 PM",
            "3:11 PM",
            "3:26 PM",
            "3:41 PM",
            "3:56 PM",
            "4:11 PM",
            "4:26 PM",
            "4:41 PM",
            "4:56 PM",
            "5:11 PM",
            "5:26 PM",
            "5:41 PM"
          ],
          "zip": "48322"
        },
        {
          "id": "gh-51992",
          "name": "GoHealth UC \u2014 Wonderland Village Livonia",
          "area": "Wonderland Village Livonia",
          "type": "Urgent Care",
          "sameDaySlots": 24,
          "nextDaySlots": 0,
          "nextAvailable": "Thu 4/16 \u2014 24 slots (first: 1:14 PM)",
          "nextAvailableDate": "Thu 4/16",
          "source": "GoHealth",
          "lastChecked": "2026-04-16T12:42:14.536227",
          "address": "29321 Plymouth Rd, Livonia, MI 48150",
          "lat": 42.368,
          "lng": -83.353,
          "times": [
            "1:14 PM",
            "1:29 PM",
            "1:44 PM",
            "1:59 PM",
            "2:14 PM",
            "2:29 PM",
            "2:44 PM",
            "2:59 PM",
            "3:14 PM",
            "3:29 PM",
            "3:44 PM",
            "3:59 PM",
            "4:14 PM",
            "4:49 PM",
            "5:04 PM",
            "5:19 PM",
            "5:34 PM",
            "5:49 PM",
            "6:04 PM",
            "6:19 PM"
          ],
          "zip": "29321"
        }
      ]
    },
    "firstchoice_uc": {
      "name": "1st Choice Urgent Care",
      "locations": [
        {
          "id": "fc-45624",
          "name": "1st Choice UC \u2014 Bloomfield",
          "area": "Bloomfield",
          "type": "Urgent Care",
          "sameDaySlots": 28,
          "nextDaySlots": 0,
          "nextAvailable": "Thu 4/16 \u2014 28 slots (first: 12:37 pm)",
          "nextAvailableDate": "Thu 4/16",
          "source": "Solv",
          "lastChecked": "2026-04-16T12:34:06.889476",
          "address": "2274 S Telegraph Rd, Bloomfield, MI 48302",
          "lat": 42.61,
          "lng": -83.28,
          "times": [
            "12:37 pm",
            "12:45 pm",
            "12:52 pm",
            "1:00 pm",
            "1:07 pm",
            "1:15 pm",
            "1:22 pm",
            "1:30 pm",
            "1:37 pm",
            "1:45 pm",
            "1:52 pm",
            "2:00 pm",
            "2:07 pm",
            "2:15 pm",
            "5:00 pm",
            "5:07 pm",
            "5:15 pm",
            "5:22 pm",
            "5:30 pm",
            "5:37 pm"
          ],
          "zip": "48302"
        },
        {
          "id": "fc-9534",
          "name": "1st Choice UC \u2014 Clinton Township",
          "area": "Clinton Township",
          "type": "Urgent Care",
          "sameDaySlots": 28,
          "nextDaySlots": 0,
          "nextAvailable": "Thu 4/16 \u2014 28 slots (first: 1:40 pm)",
          "nextAvailableDate": "Thu 4/16",
          "source": "Solv",
          "lastChecked": "2026-04-16T12:34:18.666792",
          "address": "44472 Hayes Rd, Clinton Township, MI 48038",
          "lat": 42.582,
          "lng": -82.929,
          "times": [
            "1:40 pm",
            "1:50 pm",
            "2:00 pm",
            "2:10 pm",
            "2:20 pm",
            "2:30 pm",
            "2:40 pm",
            "2:50 pm",
            "3:00 pm",
            "3:10 pm",
            "3:20 pm",
            "3:30 pm",
            "3:40 pm",
            "3:50 pm",
            "5:00 pm",
            "5:10 pm",
            "5:20 pm",
            "5:30 pm",
            "5:40 pm",
            "5:50 pm"
          ],
          "zip": "44472"
        },
        {
          "id": "fc-18552",
          "name": "1st Choice UC \u2014 Dearborn East",
          "area": "Dearborn East",
          "type": "Urgent Care",
          "sameDaySlots": 28,
          "nextDaySlots": 0,
          "nextAvailable": "Thu 4/16 \u2014 28 slots (first: 12:40 pm)",
          "nextAvailableDate": "Thu 4/16",
          "source": "Solv",
          "lastChecked": "2026-04-16T12:34:29.321265",
          "address": "12841 Ford Rd, Dearborn, MI 48126",
          "lat": 42.322,
          "lng": -83.176,
          "times": [
            "12:40 pm",
            "12:50 pm",
            "1:00 pm",
            "1:10 pm",
            "1:20 pm",
            "1:30 pm",
            "1:40 pm",
            "1:50 pm",
            "2:00 pm",
            "2:10 pm",
            "2:20 pm",
            "2:30 pm",
            "2:40 pm",
            "2:50 pm",
            "5:00 pm",
            "5:10 pm",
            "5:20 pm",
            "5:30 pm",
            "5:40 pm",
            "5:50 pm"
          ],
          "zip": "12841"
        },
        {
          "id": "fc-55742",
          "name": "1st Choice UC \u2014 Dearborn West",
          "area": "Dearborn West",
          "type": "Urgent Care",
          "sameDaySlots": 28,
          "nextDaySlots": 0,
          "nextAvailable": "Thu 4/16 \u2014 28 slots (first: 12:40 pm)",
          "nextAvailableDate": "Thu 4/16",
          "source": "Solv",
          "lastChecked": "2026-04-16T12:34:39.157041",
          "address": "23455 Michigan Ave, Dearborn, MI 48124",
          "lat": 42.322,
          "lng": -83.176,
          "times": [
            "12:40 pm",
            "12:50 pm",
            "1:00 pm",
            "1:10 pm",
            "1:20 pm",
            "1:30 pm",
            "1:40 pm",
            "1:50 pm",
            "2:00 pm",
            "2:10 pm",
            "2:20 pm",
            "2:30 pm",
            "2:40 pm",
            "2:50 pm",
            "5:00 pm",
            "5:10 pm",
            "5:20 pm",
            "5:30 pm",
            "5:40 pm",
            "5:50 pm"
          ],
          "zip": "23455"
        },
        {
          "id": "fc-19765",
          "name": "1st Choice UC \u2014 Garden City",
          "area": "Garden City",
          "type": "Urgent Care",
          "sameDaySlots": 28,
          "nextDaySlots": 0,
          "nextAvailable": "Thu 4/16 \u2014 28 slots (first: 12:40 pm)",
          "nextAvailableDate": "Thu 4/16",
          "source": "Solv",
          "lastChecked": "2026-04-16T12:34:51.031617",
          "address": "31450 Ford Rd, Garden City, MI 48135",
          "lat": 42.326,
          "lng": -83.331,
          "times": [
            "12:40 pm",
            "12:50 pm",
            "1:00 pm",
            "1:10 pm",
            "1:20 pm",
            "1:30 pm",
            "1:40 pm",
            "1:50 pm",
            "2:00 pm",
            "2:10 pm",
            "2:20 pm",
            "2:30 pm",
            "2:40 pm",
            "2:50 pm",
            "5:00 pm",
            "5:10 pm",
            "5:20 pm",
            "5:30 pm",
            "5:40 pm",
            "5:50 pm"
          ],
          "zip": "31450"
        },
        {
          "id": "fc-18113",
          "name": "1st Choice UC \u2014 Livonia",
          "area": "Livonia",
          "type": "Urgent Care",
          "sameDaySlots": 28,
          "nextDaySlots": 0,
          "nextAvailable": "Thu 4/16 \u2014 28 slots (first: 12:35 pm)",
          "nextAvailableDate": "Thu 4/16",
          "source": "Solv",
          "lastChecked": "2026-04-16T12:35:01.577658",
          "address": "11502 Middlebelt Rd, Livonia, MI 48150",
          "lat": 42.368,
          "lng": -83.353,
          "times": [
            "12:35 pm",
            "12:40 pm",
            "12:45 pm",
            "12:50 pm",
            "12:55 pm",
            "1:00 pm",
            "1:05 pm",
            "1:10 pm",
            "1:15 pm",
            "1:20 pm",
            "1:25 pm",
            "1:30 pm",
            "1:35 pm",
            "1:40 pm",
            "5:00 pm",
            "5:05 pm",
            "5:10 pm",
            "5:15 pm",
            "5:20 pm",
            "5:25 pm"
          ],
          "zip": "11502"
        },
        {
          "id": "fc-21891",
          "name": "1st Choice UC \u2014 Macomb",
          "area": "Macomb",
          "type": "Urgent Care",
          "sameDaySlots": 28,
          "nextDaySlots": 0,
          "nextAvailable": "Thu 4/16 \u2014 28 slots (first: 1:40 pm)",
          "nextAvailableDate": "Thu 4/16",
          "source": "Solv",
          "lastChecked": "2026-04-16T12:35:12.702032",
          "address": "18200 23 Mile Rd, Macomb, MI 48044",
          "lat": 42.672,
          "lng": -82.912,
          "times": [
            "1:40 pm",
            "1:50 pm",
            "2:00 pm",
            "2:10 pm",
            "2:20 pm",
            "2:30 pm",
            "2:40 pm",
            "2:50 pm",
            "3:00 pm",
            "3:10 pm",
            "3:20 pm",
            "3:30 pm",
            "3:40 pm",
            "3:50 pm",
            "5:00 pm",
            "5:10 pm",
            "5:20 pm",
            "5:30 pm",
            "5:40 pm",
            "5:50 pm"
          ],
          "zip": "18200"
        },
        {
          "id": "fc-94738",
          "name": "1st Choice UC \u2014 Oxford",
          "area": "Oxford",
          "type": "Urgent Care",
          "sameDaySlots": 28,
          "nextDaySlots": 0,
          "nextAvailable": "Thu 4/16 \u2014 28 slots (first: 1:40 pm)",
          "nextAvailableDate": "Thu 4/16",
          "source": "Solv",
          "lastChecked": "2026-04-16T12:35:22.579802",
          "address": "72 S Washington St Suite 102, Oxford, MI 48371",
          "lat": 42.82,
          "lng": -83.27,
          "times": [
            "1:40 pm",
            "1:50 pm",
            "2:00 pm",
            "2:10 pm",
            "2:20 pm",
            "2:30 pm",
            "2:40 pm",
            "2:50 pm",
            "3:00 pm",
            "3:10 pm",
            "3:20 pm",
            "3:30 pm",
            "3:40 pm",
            "3:50 pm",
            "5:00 pm",
            "5:10 pm",
            "5:20 pm",
            "5:30 pm",
            "5:40 pm",
            "5:50 pm"
          ],
          "zip": "48371"
        },
        {
          "id": "fc-12387",
          "name": "1st Choice UC \u2014 Rochester Hills",
          "area": "Rochester Hills",
          "type": "Urgent Care",
          "sameDaySlots": 28,
          "nextDaySlots": 0,
          "nextAvailable": "Thu 4/16 \u2014 28 slots (first: 1:40 pm)",
          "nextAvailableDate": "Thu 4/16",
          "source": "Solv",
          "lastChecked": "2026-04-16T12:35:32.529747",
          "address": "2952 S Rochester Rd, Rochester Hills, MI 48307",
          "lat": 42.67,
          "lng": -83.14,
          "times": [
            "1:40 pm",
            "1:50 pm",
            "2:00 pm",
            "2:10 pm",
            "2:20 pm",
            "2:30 pm",
            "2:40 pm",
            "2:50 pm",
            "3:00 pm",
            "3:10 pm",
            "3:20 pm",
            "3:30 pm",
            "3:40 pm",
            "3:50 pm",
            "5:00 pm",
            "5:10 pm",
            "5:20 pm",
            "5:30 pm",
            "5:40 pm",
            "5:50 pm"
          ],
          "zip": "48307"
        },
        {
          "id": "fc-92715",
          "name": "1st Choice UC \u2014 Romulus",
          "area": "Romulus",
          "type": "Urgent Care",
          "sameDaySlots": 28,
          "nextDaySlots": 0,
          "nextAvailable": "Thu 4/16 \u2014 28 slots (first: 1:40 pm)",
          "nextAvailableDate": "Thu 4/16",
          "source": "Solv",
          "lastChecked": "2026-04-16T12:35:43.319615",
          "address": "29750 Ecorse Rd, Romulus, MI 48174",
          "lat": 42.222,
          "lng": -83.393,
          "times": [
            "1:40 pm",
            "1:50 pm",
            "2:00 pm",
            "2:10 pm",
            "2:20 pm",
            "2:30 pm",
            "2:40 pm",
            "2:50 pm",
            "3:00 pm",
            "3:10 pm",
            "3:20 pm",
            "3:30 pm",
            "3:40 pm",
            "3:50 pm",
            "5:00 pm",
            "5:10 pm",
            "5:20 pm",
            "5:30 pm",
            "5:40 pm",
            "5:50 pm"
          ],
          "zip": "29750"
        },
        {
          "id": "fc-43656",
          "name": "1st Choice UC \u2014 Royal Oak",
          "area": "Royal Oak",
          "type": "Urgent Care",
          "sameDaySlots": 28,
          "nextDaySlots": 0,
          "nextAvailable": "Thu 4/16 \u2014 28 slots (first: 1:40 pm)",
          "nextAvailableDate": "Thu 4/16",
          "source": "Solv",
          "lastChecked": "2026-04-16T12:35:53.536441",
          "address": "4080 Crooks Rd, Royal Oak, MI 48073",
          "lat": 42.52,
          "lng": -83.16,
          "times": [
            "1:40 pm",
            "1:50 pm",
            "2:00 pm",
            "2:10 pm",
            "2:20 pm",
            "2:30 pm",
            "2:40 pm",
            "2:50 pm",
            "3:00 pm",
            "3:10 pm",
            "3:20 pm",
            "3:30 pm",
            "3:40 pm",
            "3:50 pm",
            "5:00 pm",
            "5:10 pm",
            "5:20 pm",
            "5:30 pm",
            "5:40 pm",
            "5:50 pm"
          ],
          "zip": "48073"
        },
        {
          "id": "fc-95672",
          "name": "1st Choice UC \u2014 Saint Clair Shores",
          "area": "Saint Clair Shores",
          "type": "Urgent Care",
          "sameDaySlots": 28,
          "nextDaySlots": 0,
          "nextAvailable": "Thu 4/16 \u2014 28 slots (first: 1:40 pm)",
          "nextAvailableDate": "Thu 4/16",
          "source": "Solv",
          "lastChecked": "2026-04-16T12:36:03.275269",
          "address": "25515 Harper Ave, Saint Clair Shores, MI 48081",
          "lat": 42.497,
          "lng": -82.891,
          "times": [
            "1:40 pm",
            "1:50 pm",
            "2:00 pm",
            "2:10 pm",
            "2:20 pm",
            "2:30 pm",
            "2:40 pm",
            "2:50 pm",
            "3:00 pm",
            "3:10 pm",
            "3:20 pm",
            "3:30 pm",
            "3:40 pm",
            "3:50 pm",
            "5:00 pm",
            "5:10 pm",
            "5:20 pm",
            "5:30 pm",
            "5:40 pm",
            "5:50 pm"
          ],
          "zip": "25515"
        },
        {
          "id": "fc-85339",
          "name": "1st Choice UC \u2014 Southfield",
          "area": "Southfield",
          "type": "Urgent Care",
          "sameDaySlots": 28,
          "nextDaySlots": 0,
          "nextAvailable": "Thu 4/16 \u2014 28 slots (first: 12:37 pm)",
          "nextAvailableDate": "Thu 4/16",
          "source": "Solv",
          "lastChecked": "2026-04-16T12:36:13.977122",
          "address": "29628 Southfield Rd, Southfield, MI 48076",
          "lat": 42.473,
          "lng": -83.222,
          "times": [
            "12:37 pm",
            "12:45 pm",
            "12:52 pm",
            "1:00 pm",
            "1:07 pm",
            "1:15 pm",
            "1:22 pm",
            "1:30 pm",
            "1:37 pm",
            "1:45 pm",
            "1:52 pm",
            "2:00 pm",
            "2:07 pm",
            "2:15 pm",
            "5:00 pm",
            "5:07 pm",
            "5:15 pm",
            "5:22 pm",
            "5:30 pm",
            "5:37 pm"
          ],
          "zip": "29628"
        },
        {
          "id": "fc-97464",
          "name": "1st Choice UC \u2014 Taylor",
          "area": "Taylor",
          "type": "Urgent Care",
          "sameDaySlots": 14,
          "nextDaySlots": 0,
          "nextAvailable": "Thu 4/16 \u2014 14 slots (first: 12:40 pm)",
          "nextAvailableDate": "Thu 4/16",
          "source": "Solv",
          "lastChecked": "2026-04-16T12:36:24.549756",
          "address": "10155 Telegraph Rd, Taylor, MI 48180",
          "lat": 42.241,
          "lng": -83.269,
          "times": [
            "12:40 pm",
            "12:50 pm",
            "1:00 pm",
            "1:10 pm",
            "1:20 pm",
            "1:30 pm",
            "1:40 pm",
            "1:50 pm",
            "2:00 pm",
            "2:10 pm",
            "2:20 pm",
            "2:30 pm",
            "2:40 pm",
            "2:50 pm"
          ],
          "zip": "10155"
        },
        {
          "id": "fc-83692",
          "name": "1st Choice UC \u2014 Warren",
          "area": "Warren",
          "type": "Urgent Care",
          "sameDaySlots": 28,
          "nextDaySlots": 0,
          "nextAvailable": "Thu 4/16 \u2014 28 slots (first: 12:40 pm)",
          "nextAvailableDate": "Thu 4/16",
          "source": "Solv",
          "lastChecked": "2026-04-16T12:36:35.040029",
          "address": "25600 Schoenherr Rd, Warren, MI 48089",
          "lat": 42.49,
          "lng": -83.027,
          "times": [
            "12:40 pm",
            "12:50 pm",
            "1:00 pm",
            "1:10 pm",
            "1:20 pm",
            "1:30 pm",
            "1:40 pm",
            "1:50 pm",
            "2:00 pm",
            "2:10 pm",
            "2:20 pm",
            "2:30 pm",
            "2:40 pm",
            "2:50 pm",
            "5:00 pm",
            "5:10 pm",
            "5:20 pm",
            "5:30 pm",
            "5:40 pm",
            "5:50 pm"
          ],
          "zip": "25600"
        },
        {
          "id": "fc-33876",
          "name": "1st Choice UC \u2014 Washington",
          "area": "Washington",
          "type": "Urgent Care",
          "sameDaySlots": 28,
          "nextDaySlots": 0,
          "nextAvailable": "Thu 4/16 \u2014 28 slots (first: 1:40 pm)",
          "nextAvailableDate": "Thu 4/16",
          "source": "Solv",
          "lastChecked": "2026-04-16T12:36:45.464892",
          "address": "7701 26 Mile Rd, Washington, MI 48094",
          "lat": 42.736,
          "lng": -83.035,
          "times": [
            "1:40 pm",
            "1:50 pm",
            "2:00 pm",
            "2:10 pm",
            "2:20 pm",
            "2:30 pm",
            "2:40 pm",
            "2:50 pm",
            "3:00 pm",
            "3:10 pm",
            "3:20 pm",
            "3:30 pm",
            "3:40 pm",
            "3:50 pm",
            "5:00 pm",
            "5:10 pm",
            "5:20 pm",
            "5:30 pm",
            "5:40 pm",
            "5:50 pm"
          ],
          "zip": "48094"
        },
        {
          "id": "fc-20933",
          "name": "1st Choice UC \u2014 Waterford",
          "area": "Waterford",
          "type": "Urgent Care",
          "sameDaySlots": 28,
          "nextDaySlots": 0,
          "nextAvailable": "Thu 4/16 \u2014 28 slots (first: 1:40 pm)",
          "nextAvailableDate": "Thu 4/16",
          "source": "Solv",
          "lastChecked": "2026-04-16T12:36:55.535649",
          "address": "2446 Elizabeth Lake, Waterford, MI 48328",
          "lat": 42.62,
          "lng": -83.38,
          "times": [
            "1:40 pm",
            "1:50 pm",
            "2:00 pm",
            "2:10 pm",
            "2:20 pm",
            "2:30 pm",
            "2:40 pm",
            "2:50 pm",
            "3:00 pm",
            "3:10 pm",
            "3:20 pm",
            "3:30 pm",
            "3:40 pm",
            "3:50 pm",
            "5:00 pm",
            "5:10 pm",
            "5:20 pm",
            "5:30 pm",
            "5:40 pm",
            "5:50 pm"
          ],
          "zip": "48328"
        },
        {
          "id": "fc-55862",
          "name": "1st Choice UC \u2014 Ypsilanti",
          "area": "Ypsilanti",
          "type": "Urgent Care",
          "sameDaySlots": 28,
          "nextDaySlots": 0,
          "nextAvailable": "Thu 4/16 \u2014 28 slots (first: 1:40 pm)",
          "nextAvailableDate": "Thu 4/16",
          "source": "Solv",
          "lastChecked": "2026-04-16T12:37:05.065200",
          "address": "494 N Hewitt Rd, Ypsilanti, MI 48197",
          "lat": 42.22,
          "lng": -83.62,
          "times": [
            "1:40 pm",
            "1:50 pm",
            "2:00 pm",
            "2:10 pm",
            "2:20 pm",
            "2:30 pm",
            "2:40 pm",
            "2:50 pm",
            "3:00 pm",
            "3:10 pm",
            "3:20 pm",
            "3:30 pm",
            "3:40 pm",
            "3:50 pm",
            "5:00 pm",
            "5:10 pm",
            "5:20 pm",
            "5:30 pm",
            "5:40 pm",
            "5:50 pm"
          ],
          "zip": "48197"
        }
      ]
    },
    "corewell_pc": {
      "name": "Corewell Health Primary Care",
      "locations": [
        {
          "id": "cpc-18039",
          "name": "Corewell Health Internal Medicine",
          "area": "Troy",
          "type": "Primary Care",
          "sameDaySlots": 0,
          "nextDaySlots": 1,
          "nextAvailable": "Fri 4/17 \u2014 1 slots (first: 1:00 PM)",
          "nextAvailableDate": "Fri 4/17",
          "source": "MyChart",
          "lastChecked": "2026-04-16T12:33:49.696289",
          "address": "38865 Dequindre Rd Ste 106 Troy MI 48083-6812",
          "lat": 42.606,
          "lng": -83.15,
          "times": [],
          "zip": "38865"
        },
        {
          "id": "cpc-45138",
          "name": "Corewell Health Primary Care",
          "area": "Mile Rd Saint Clair Shores",
          "type": "Primary Care",
          "sameDaySlots": 0,
          "nextDaySlots": 3,
          "nextAvailable": "Fri 4/17 \u2014 3 slots (first: 9:00 AM)",
          "nextAvailableDate": "Fri 4/17",
          "source": "MyChart",
          "lastChecked": "2026-04-16T12:33:49.696405",
          "address": "21400 E 11 Mile Rd Saint Clair Shores MI 48081-1566",
          "lat": 42.497,
          "lng": -82.891,
          "times": [],
          "zip": "21400"
        },
        {
          "id": "cpc-56474",
          "name": "Corewell Health Internal Medicine",
          "area": "Roseville",
          "type": "Primary Care",
          "sameDaySlots": 0,
          "nextDaySlots": 1,
          "nextAvailable": "Fri 4/17 \u2014 1 slots (first: 1:30 PM)",
          "nextAvailableDate": "Fri 4/17",
          "source": "MyChart",
          "lastChecked": "2026-04-16T12:33:49.696497",
          "address": "18325 E 10 Mile Rd Ste 300 Roseville MI 48066-4990",
          "lat": 42.497,
          "lng": -82.937,
          "times": [],
          "zip": "18325"
        },
        {
          "id": "cpc-33154",
          "name": "Corewell Health Internal Medicine - Midway with Kristin Iannotti.",
          "area": "Rochester Hills",
          "type": "Primary Care",
          "sameDaySlots": 0,
          "nextDaySlots": 3,
          "nextAvailable": "Fri 4/17 \u2014 3 slots (first: 1:30 PM)",
          "nextAvailableDate": "Fri 4/17",
          "source": "MyChart",
          "lastChecked": "2026-04-16T12:33:49.696624",
          "address": "555 Barclay Cir Ste 150 Rochester Hills MI 48307-4587",
          "lat": 42.67,
          "lng": -83.14,
          "times": [],
          "zip": "48307"
        },
        {
          "id": "cpc-1012",
          "name": "Corewell Health Family Medicine",
          "area": "Roseville",
          "type": "Primary Care",
          "sameDaySlots": 0,
          "nextDaySlots": 1,
          "nextAvailable": "Fri 4/17 \u2014 1 slots (first: 8:00 AM)",
          "nextAvailableDate": "Fri 4/17",
          "source": "MyChart",
          "lastChecked": "2026-04-16T12:33:49.696713",
          "address": "30695 Little Mack Ave Ste 200 Roseville MI 48066-1781",
          "lat": 42.497,
          "lng": -82.937,
          "times": [],
          "zip": "30695"
        },
        {
          "id": "cpc-77565",
          "name": "Corewell Health Family Medicine",
          "area": "Warren St Dearborn Heights",
          "type": "Primary Care",
          "sameDaySlots": 0,
          "nextDaySlots": 0,
          "nextAvailable": "Mon 4/20 \u2014 36 slots (first: 3:15 PM)",
          "nextAvailableDate": "Mon 4/20",
          "source": "MyChart",
          "lastChecked": "2026-04-16T12:33:49.696784",
          "address": "27031 W Warren St Dearborn Heights MI 48127-1901",
          "lat": 42.337,
          "lng": -83.273,
          "times": [],
          "zip": "27031"
        },
        {
          "id": "cpc-38554",
          "name": "Corewell Health Family Medicine - Livonia/Northville",
          "area": "Livonia",
          "type": "Primary Care",
          "sameDaySlots": 0,
          "nextDaySlots": 0,
          "nextAvailable": "Mon 4/20 \u2014 14 slots (first: 11:00 AM)",
          "nextAvailableDate": "Mon 4/20",
          "source": "MyChart",
          "lastChecked": "2026-04-16T12:33:49.696852",
          "address": "39000 7 Mile Rd Ste 4300 Livonia MI 48152-1006",
          "lat": 42.368,
          "lng": -83.353,
          "times": [],
          "zip": "39000"
        },
        {
          "id": "cpc-23716",
          "name": "Corewell Health Family Medicine",
          "area": "Dix Toledo Rd Southgate",
          "type": "Primary Care",
          "sameDaySlots": 0,
          "nextDaySlots": 0,
          "nextAvailable": "Mon 4/20 \u2014 12 slots (first: 12:00 PM)",
          "nextAvailableDate": "Mon 4/20",
          "source": "MyChart",
          "lastChecked": "2026-04-16T12:33:49.696910",
          "address": "14319 Dix Toledo Rd Southgate MI 48195-2506",
          "lat": 42.214,
          "lng": -83.194,
          "times": [],
          "zip": "14319"
        },
        {
          "id": "cpc-73312",
          "name": "Corewell Health Pediatrics",
          "area": "Canton",
          "type": "Primary Care",
          "sameDaySlots": 0,
          "nextDaySlots": 0,
          "nextAvailable": "Mon 4/20 \u2014 15 slots (first: 8:00 AM)",
          "nextAvailableDate": "Mon 4/20",
          "source": "MyChart",
          "lastChecked": "2026-04-16T12:33:49.696963",
          "address": "7330 N Canton Center Rd Ste 216 Canton MI 48187-1538",
          "lat": 42.26,
          "lng": -83.38,
          "times": [],
          "zip": "48187"
        },
        {
          "id": "cpc-69578",
          "name": "Corewell Health Family Medicine - Garden City",
          "area": "Ford Rd Garden City",
          "type": "Primary Care",
          "sameDaySlots": 0,
          "nextDaySlots": 0,
          "nextAvailable": "Mon 4/20 \u2014 18 slots (first: 2:00 PM)",
          "nextAvailableDate": "Mon 4/20",
          "source": "MyChart",
          "lastChecked": "2026-04-16T12:33:49.697019",
          "address": "29150 Ford Rd Garden City MI 48135-2848",
          "lat": 42.326,
          "lng": -83.331,
          "times": [],
          "zip": "29150"
        },
        {
          "id": "cpc-35910",
          "name": "Corewell Health Family Medicine",
          "area": "Warren",
          "type": "Primary Care",
          "sameDaySlots": 0,
          "nextDaySlots": 0,
          "nextAvailable": "Mon 4/20 \u2014 10 slots (first: 1:30 PM)",
          "nextAvailableDate": "Mon 4/20",
          "source": "MyChart",
          "lastChecked": "2026-04-16T12:33:49.697065",
          "address": "8545 Common Rd Ste 280 Warren MI 48093-6775",
          "lat": 42.53,
          "lng": -83.05,
          "times": [],
          "zip": "48093"
        },
        {
          "id": "cpc-52149",
          "name": "Corewell Health Family Medicine",
          "area": "Dearborn",
          "type": "Primary Care",
          "sameDaySlots": 0,
          "nextDaySlots": 0,
          "nextAvailable": "Mon 4/20 \u2014 12 slots (first: 8:30 AM)",
          "nextAvailableDate": "Mon 4/20",
          "source": "MyChart",
          "lastChecked": "2026-04-16T12:33:49.697112",
          "address": "4700 Schaefer Rd Ste 150 Dearborn MI 48126-3655",
          "lat": 42.33,
          "lng": -83.18,
          "times": [],
          "zip": "48126"
        },
        {
          "id": "cpc-42694",
          "name": "Corewell Health Family Medicine",
          "area": "Grand River Ave Farmington",
          "type": "Primary Care",
          "sameDaySlots": 0,
          "nextDaySlots": 0,
          "nextAvailable": "Mon 4/20 \u2014 8 slots (first: 12:30 PM)",
          "nextAvailableDate": "Mon 4/20",
          "source": "MyChart",
          "lastChecked": "2026-04-16T12:33:49.697165",
          "address": "32754 Grand River Ave Farmington MI 48336-3133",
          "lat": 42.465,
          "lng": -83.377,
          "times": [],
          "zip": "32754"
        },
        {
          "id": "cpc-94244",
          "name": "Corewell Health Internal Medicine",
          "area": "Westland",
          "type": "Primary Care",
          "sameDaySlots": 0,
          "nextDaySlots": 0,
          "nextAvailable": "Mon 4/20 \u2014 17 slots (first: 2:00 PM)",
          "nextAvailableDate": "Mon 4/20",
          "source": "MyChart",
          "lastChecked": "2026-04-16T12:33:49.697279",
          "address": "35330 Nankin Blvd Ste 701 Westland MI 48185-7223",
          "lat": 42.324,
          "lng": -83.4,
          "times": [],
          "zip": "35330"
        },
        {
          "id": "cpc-26591",
          "name": "Corewell Health Internal Medicine",
          "area": "Farmington Rd Livonia",
          "type": "Primary Care",
          "sameDaySlots": 0,
          "nextDaySlots": 0,
          "nextAvailable": "Mon 4/20 \u2014 11 slots (first: 8:30 AM)",
          "nextAvailableDate": "Mon 4/20",
          "source": "MyChart",
          "lastChecked": "2026-04-16T12:33:49.697335",
          "address": "20317 Farmington Rd Livonia MI 48152-1411",
          "lat": 42.465,
          "lng": -83.377,
          "times": [],
          "zip": "20317"
        },
        {
          "id": "cpc-60025",
          "name": "Corewell Health Children's Pediatrics",
          "area": "Southgate",
          "type": "Primary Care",
          "sameDaySlots": 0,
          "nextDaySlots": 0,
          "nextAvailable": "Mon 4/20 \u2014 2 slots (first: 8:45 AM)",
          "nextAvailableDate": "Mon 4/20",
          "source": "MyChart",
          "lastChecked": "2026-04-16T12:33:49.697390",
          "address": "15777 Northline Rd Ste 200 Southgate MI 48195-2354",
          "lat": 42.214,
          "lng": -83.194,
          "times": [],
          "zip": "15777"
        },
        {
          "id": "cpc-42658",
          "name": "Corewell Health Internal Medicine",
          "area": "Hubbard Dr Dearborn",
          "type": "Primary Care",
          "sameDaySlots": 0,
          "nextDaySlots": 0,
          "nextAvailable": "Mon 4/20 \u2014 13 slots (first: 9:30 AM)",
          "nextAvailableDate": "Mon 4/20",
          "source": "MyChart",
          "lastChecked": "2026-04-16T12:33:49.697444",
          "address": "17000 Hubbard Dr Dearborn MI 48126-4258",
          "lat": 42.322,
          "lng": -83.176,
          "times": [],
          "zip": "17000"
        },
        {
          "id": "cpc-14102",
          "name": "Corewell Health Primary Care",
          "area": "Grosse Pointe",
          "type": "Primary Care",
          "sameDaySlots": 0,
          "nextDaySlots": 0,
          "nextAvailable": "Mon 4/20 \u2014 36 slots (first: 11:00 AM)",
          "nextAvailableDate": "Mon 4/20",
          "source": "MyChart",
          "lastChecked": "2026-04-16T12:33:49.697500",
          "address": "17000 Kercheval Ave Ste 205 Grosse Pointe MI 48230-1570",
          "lat": 42.387,
          "lng": -82.906,
          "times": [],
          "zip": "17000"
        },
        {
          "id": "cpc-22923",
          "name": "Corewell Health Primary Care",
          "area": "Kercheval Ave Grosse Pointe Park",
          "type": "Primary Care",
          "sameDaySlots": 0,
          "nextDaySlots": 0,
          "nextAvailable": "Mon 4/20 \u2014 28 slots (first: 8:45 AM)",
          "nextAvailableDate": "Mon 4/20",
          "source": "MyChart",
          "lastChecked": "2026-04-16T12:33:49.697554",
          "address": "15200 Kercheval Ave Grosse Pointe Park MI 48230-1356",
          "lat": 42.387,
          "lng": -82.906,
          "times": [],
          "zip": "15200"
        },
        {
          "id": "cpc-87664",
          "name": "Corewell Health Pediatrics",
          "area": "Orchard Lake Rd Farmington",
          "type": "Primary Care",
          "sameDaySlots": 0,
          "nextDaySlots": 0,
          "nextAvailable": "Mon 4/20 \u2014 9 slots (first: 8:20 AM)",
          "nextAvailableDate": "Mon 4/20",
          "source": "MyChart",
          "lastChecked": "2026-04-16T12:33:49.697604",
          "address": "23133 Orchard Lake Rd Farmington MI 48336-3268",
          "lat": 42.465,
          "lng": -83.377,
          "times": [],
          "zip": "23133"
        },
        {
          "id": "cpc-2559",
          "name": "Corewell Health Family Medicine - Newport",
          "area": "Newport Rd Newport",
          "type": "Primary Care",
          "sameDaySlots": 0,
          "nextDaySlots": 0,
          "nextAvailable": "Mon 4/20 \u2014 12 slots (first: 8:00 AM)",
          "nextAvailableDate": "Mon 4/20",
          "source": "MyChart",
          "lastChecked": "2026-04-16T12:33:49.697660",
          "address": "3132 Newport Rd Newport MI 48166-6100",
          "lat": null,
          "lng": null,
          "times": [],
          "zip": "48166"
        },
        {
          "id": "cpc-97059",
          "name": "Corewell Health Family Medicine",
          "area": "Mile Rd Novi",
          "type": "Primary Care",
          "sameDaySlots": 0,
          "nextDaySlots": 0,
          "nextAvailable": "Mon 4/20 \u2014 11 slots (first: 9:30 AM)",
          "nextAvailableDate": "Mon 4/20",
          "source": "MyChart",
          "lastChecked": "2026-04-16T12:33:49.697714",
          "address": "44130 W 12 Mile Rd Novi MI 48377-2614",
          "lat": 42.48,
          "lng": -83.476,
          "times": [],
          "zip": "44130"
        },
        {
          "id": "cpc-80996",
          "name": "Corewell Health Internal Medicine",
          "area": "Biddle Ave Wyandotte",
          "type": "Primary Care",
          "sameDaySlots": 0,
          "nextDaySlots": 0,
          "nextAvailable": "Mon 4/20 \u2014 13 slots (first: 8:30 AM)",
          "nextAvailableDate": "Mon 4/20",
          "source": "MyChart",
          "lastChecked": "2026-04-16T12:33:49.697757",
          "address": "1700 Biddle Ave Wyandotte MI 48192-7205",
          "lat": 42.21,
          "lng": -83.18,
          "times": [],
          "zip": "48192"
        },
        {
          "id": "cpc-35142",
          "name": "Corewell Health Internal Medicine",
          "area": "Southfield",
          "type": "Primary Care",
          "sameDaySlots": 0,
          "nextDaySlots": 0,
          "nextAvailable": "Mon 4/20 \u2014 5 slots (first: 1:15 PM)",
          "nextAvailableDate": "Mon 4/20",
          "source": "MyChart",
          "lastChecked": "2026-04-16T12:33:49.697810",
          "address": "29355 Northwestern Hwy Ste 210 Southfield MI 48034-1045",
          "lat": 42.473,
          "lng": -83.222,
          "times": [],
          "zip": "29355"
        },
        {
          "id": "cpc-57152",
          "name": "Corewell Health Internal Medicine",
          "area": "Warren St Dearborn Heights",
          "type": "Primary Care",
          "sameDaySlots": 0,
          "nextDaySlots": 0,
          "nextAvailable": "Mon 4/20 \u2014 20 slots (first: 10:30 AM)",
          "nextAvailableDate": "Mon 4/20",
          "source": "MyChart",
          "lastChecked": "2026-04-16T12:33:49.697865",
          "address": "27015 W Warren St Dearborn Heights MI 48127-1901",
          "lat": 42.337,
          "lng": -83.273,
          "times": [],
          "zip": "27015"
        },
        {
          "id": "cpc-82899",
          "name": "Corewell Health Family Medicine - Belleville",
          "area": "St Belleville",
          "type": "Primary Care",
          "sameDaySlots": 0,
          "nextDaySlots": 0,
          "nextAvailable": "Mon 4/20 \u2014 10 slots (first: 9:30 AM)",
          "nextAvailableDate": "Mon 4/20",
          "source": "MyChart",
          "lastChecked": "2026-04-16T12:33:49.697911",
          "address": "201 3rd St Belleville MI 48111-2605",
          "lat": 42.15,
          "lng": -83.36,
          "times": [],
          "zip": "48111"
        },
        {
          "id": "cpc-12094",
          "name": "Corewell Health Family Medicine",
          "area": "Canton",
          "type": "Primary Care",
          "sameDaySlots": 0,
          "nextDaySlots": 0,
          "nextAvailable": "Mon 4/20 \u2014 20 slots (first: 10:30 AM)",
          "nextAvailableDate": "Mon 4/20",
          "source": "MyChart",
          "lastChecked": "2026-04-16T12:33:49.697958",
          "address": "2050 N Haggerty Rd Ste 220 Canton MI 48187-3796",
          "lat": 42.26,
          "lng": -83.38,
          "times": [],
          "zip": "48187"
        },
        {
          "id": "cpc-95229",
          "name": "Corewell Health Family Medicine - Livonia/Northville with Kerry Stone.",
          "area": "Livonia",
          "type": "Primary Care",
          "sameDaySlots": 0,
          "nextDaySlots": 0,
          "nextAvailable": "Mon 4/20 \u2014 14 slots (first: 8:30 AM)",
          "nextAvailableDate": "Mon 4/20",
          "source": "MyChart",
          "lastChecked": "2026-04-16T12:33:49.698018",
          "address": "39000 7 Mile Rd Ste 4300 Livonia MI 48152-1006",
          "lat": 42.368,
          "lng": -83.353,
          "times": [],
          "zip": "39000"
        },
        {
          "id": "cpc-49833",
          "name": "Corewell Health Family Medicine",
          "area": "Plaza Dr Taylor",
          "type": "Primary Care",
          "sameDaySlots": 0,
          "nextDaySlots": 0,
          "nextAvailable": "Mon 4/20 \u2014 10 slots (first: 9:30 AM)",
          "nextAvailableDate": "Mon 4/20",
          "source": "MyChart",
          "lastChecked": "2026-04-16T12:33:49.698072",
          "address": "15100 S Plaza Dr Taylor MI 48180-5203",
          "lat": 42.241,
          "lng": -83.269,
          "times": [],
          "zip": "15100"
        },
        {
          "id": "cpc-11609",
          "name": "Corewell Health Internal Medicine",
          "area": "Canton",
          "type": "Primary Care",
          "sameDaySlots": 0,
          "nextDaySlots": 0,
          "nextAvailable": "Tue 4/21 \u2014 6 slots (first: 10:30 AM)",
          "nextAvailableDate": "Tue 4/21",
          "source": "MyChart",
          "lastChecked": "2026-04-16T12:33:49.698118",
          "address": "7330 N Canton Center Rd Ste 209 Canton MI 48187-1538",
          "lat": 42.26,
          "lng": -83.38,
          "times": [],
          "zip": "48187"
        },
        {
          "id": "cpc-76433",
          "name": "Corewell Health Internal Medicine",
          "area": "Warren St Dearborn Heights",
          "type": "Primary Care",
          "sameDaySlots": 0,
          "nextDaySlots": 0,
          "nextAvailable": "Tue 4/21 \u2014 19 slots (first: 11:15 AM)",
          "nextAvailableDate": "Tue 4/21",
          "source": "MyChart",
          "lastChecked": "2026-04-16T12:33:49.698169",
          "address": "27015 W Warren St Dearborn Heights MI 48127-1901",
          "lat": 42.337,
          "lng": -83.273,
          "times": [],
          "zip": "27015"
        },
        {
          "id": "cpc-14673",
          "name": "Corewell Health Internal Medicine",
          "area": "Mile Rd Beverly Hills",
          "type": "Primary Care",
          "sameDaySlots": 0,
          "nextDaySlots": 0,
          "nextAvailable": "Tue 4/21 \u2014 1 slots (first: 2:30 PM)",
          "nextAvailableDate": "Tue 4/21",
          "source": "MyChart",
          "lastChecked": "2026-04-16T12:33:49.698223",
          "address": "17392 W 13 Mile Rd Beverly Hills MI 48025-5438",
          "lat": null,
          "lng": null,
          "times": [],
          "zip": "17392"
        },
        {
          "id": "cpc-268",
          "name": "Corewell Health Family Medicine",
          "area": "Farmington Hills",
          "type": "Primary Care",
          "sameDaySlots": 0,
          "nextDaySlots": 0,
          "nextAvailable": "Tue 4/21 \u2014 3 slots (first: 1:30 PM)",
          "nextAvailableDate": "Tue 4/21",
          "source": "MyChart",
          "lastChecked": "2026-04-16T12:33:49.698275",
          "address": "29645 W 14 Mile Rd Ste 110 Farmington Hills MI 48334-1666",
          "lat": 42.498,
          "lng": -83.377,
          "times": [],
          "zip": "29645"
        },
        {
          "id": "cpc-12045",
          "name": "Corewell Health Internal Medicine",
          "area": "Canton",
          "type": "Primary Care",
          "sameDaySlots": 0,
          "nextDaySlots": 0,
          "nextAvailable": "Tue 4/21 \u2014 7 slots (first: 2:30 PM)",
          "nextAvailableDate": "Tue 4/21",
          "source": "MyChart",
          "lastChecked": "2026-04-16T12:33:49.698320",
          "address": "2050 N Haggerty Rd Ste 100 Canton MI 48187-3796",
          "lat": 42.26,
          "lng": -83.38,
          "times": [],
          "zip": "48187"
        },
        {
          "id": "cpc-58071",
          "name": "Corewell Health Internal Medicine",
          "area": "Biddle Ave Wyandotte",
          "type": "Primary Care",
          "sameDaySlots": 0,
          "nextDaySlots": 0,
          "nextAvailable": "Wed 4/22 \u2014 3 slots (first: 8:30 AM)",
          "nextAvailableDate": "Wed 4/22",
          "source": "MyChart",
          "lastChecked": "2026-04-16T12:33:49.698366",
          "address": "1700 Biddle Ave Wyandotte MI 48192-7205",
          "lat": 42.21,
          "lng": -83.18,
          "times": [],
          "zip": "48192"
        },
        {
          "id": "cpc-73705",
          "name": "Corewell Health Family Medicine",
          "area": "Canton",
          "type": "Primary Care",
          "sameDaySlots": 0,
          "nextDaySlots": 0,
          "nextAvailable": "Wed 4/22 \u2014 1 slots (first: 2:30 PM)",
          "nextAvailableDate": "Wed 4/22",
          "source": "MyChart",
          "lastChecked": "2026-04-16T12:33:49.698410",
          "address": "7330 N Canton Center Rd Ste 111 Canton MI 48187-1538",
          "lat": 42.26,
          "lng": -83.38,
          "times": [],
          "zip": "48187"
        },
        {
          "id": "cpc-27371",
          "name": "Corewell Health Family Medicine",
          "area": "Main St Royal Oak",
          "type": "Primary Care",
          "sameDaySlots": 0,
          "nextDaySlots": 0,
          "nextAvailable": "Wed 4/22 \u2014 1 slots (first: 11:00 AM)",
          "nextAvailableDate": "Wed 4/22",
          "source": "MyChart",
          "lastChecked": "2026-04-16T12:33:49.698450",
          "address": "950 N Main St Royal Oak MI 48067-1840",
          "lat": 42.49,
          "lng": -83.14,
          "times": [],
          "zip": "48067"
        },
        {
          "id": "cpc-9268",
          "name": "Corewell Health Pediatric Clinic - Dearborn",
          "area": "Dearborn",
          "type": "Primary Care",
          "sameDaySlots": 0,
          "nextDaySlots": 0,
          "nextAvailable": "Thu 4/23 \u2014 1 slots (first: 1:00 PM)",
          "nextAvailableDate": "Thu 4/23",
          "source": "MyChart",
          "lastChecked": "2026-04-16T12:33:49.698504",
          "address": "18181 Oakwood Blvd Ste 401 Dearborn MI 48124-5031",
          "lat": 42.322,
          "lng": -83.176,
          "times": [],
          "zip": "18181"
        },
        {
          "id": "cpc-22281",
          "name": "Corewell Health Family Medicine",
          "area": "Rd Saint Clair Shores",
          "type": "Primary Care",
          "sameDaySlots": 0,
          "nextDaySlots": 0,
          "nextAvailable": "Fri 4/24 \u2014 1 slots (first: 9:00 AM)",
          "nextAvailableDate": "Fri 4/24",
          "source": "MyChart",
          "lastChecked": "2026-04-16T12:33:49.698552",
          "address": "22646 E 9 MIle Rd Saint Clair Shores MI 48080-1951",
          "lat": 42.497,
          "lng": -82.891,
          "times": [],
          "zip": "22646"
        }
      ]
    },
    "corewell_uc": {
      "name": "Corewell Health Urgent Care",
      "locations": [
        {
          "id": "cuc-1",
          "name": "Corewell UC \u2014 Rochester Hills",
          "area": "Rochester Hills",
          "type": "Urgent Care",
          "sameDaySlots": 10,
          "nextDaySlots": 0,
          "nextAvailable": "Today \u2014 10 slots (next: 12:32)",
          "nextAvailableDate": "Today",
          "source": "corewellhealthurgentcarese.com",
          "lastChecked": "2026-04-16T12:30:50.072989",
          "address": "3200 Walton Boulevard Rochester Hills, MI",
          "lat": 42.659,
          "lng": -83.15,
          "times": [
            "12:32",
            "12:35",
            "12:38",
            "12:40",
            "12:43",
            "12:46",
            "12:51",
            "12:54",
            "12:57",
            "01:00"
          ],
          "zip": ""
        },
        {
          "id": "cuc-2",
          "name": "Corewell UC \u2014 Lake Orion",
          "area": "Lake Orion",
          "type": "Urgent Care",
          "sameDaySlots": 10,
          "nextDaySlots": 0,
          "nextAvailable": "Today \u2014 10 slots (next: 12:30)",
          "nextAvailableDate": "Today",
          "source": "corewellhealthurgentcarese.com",
          "lastChecked": "2026-04-16T12:30:50.073126",
          "address": "845 S. Lapeer Rd. Orion Charter Township, MI",
          "lat": 42.782,
          "lng": -83.243,
          "times": [
            "12:30",
            "12:32",
            "12:35",
            "12:38",
            "12:40",
            "12:43",
            "12:46",
            "12:49",
            "12:51",
            "12:54"
          ],
          "zip": ""
        },
        {
          "id": "cuc-3",
          "name": "Corewell UC \u2014 Troy Big Beaver",
          "area": "Troy Big Beaver",
          "type": "Urgent Care",
          "sameDaySlots": 10,
          "nextDaySlots": 0,
          "nextAvailable": "Today \u2014 10 slots (next: 12:30)",
          "nextAvailableDate": "Today",
          "source": "corewellhealthurgentcarese.com",
          "lastChecked": "2026-04-16T12:30:50.073218",
          "address": "2078 E. Big Beaver Road Troy, MI",
          "lat": 42.606,
          "lng": -83.15,
          "times": [
            "12:30",
            "12:37",
            "12:45",
            "12:52",
            "01:00",
            "01:10",
            "01:20",
            "01:30",
            "02:00",
            "02:10"
          ],
          "zip": ""
        },
        {
          "id": "cuc-4",
          "name": "Corewell UC \u2014 Macomb",
          "area": "Macomb",
          "type": "Urgent Care",
          "sameDaySlots": 10,
          "nextDaySlots": 0,
          "nextAvailable": "Today \u2014 10 slots (next: 12:30)",
          "nextAvailableDate": "Today",
          "source": "corewellhealthurgentcarese.com",
          "lastChecked": "2026-04-16T12:30:50.073302",
          "address": "15959 Hall Road Macomb, MI",
          "lat": 42.672,
          "lng": -82.912,
          "times": [
            "12:30",
            "12:34",
            "12:38",
            "12:42",
            "12:47",
            "12:51",
            "12:55",
            "01:00",
            "01:05",
            "01:10"
          ],
          "zip": "15959"
        },
        {
          "id": "cuc-5",
          "name": "Corewell UC \u2014 Royal Oak Woodward Corners",
          "area": "Royal Oak Woodward Corners",
          "type": "Urgent Care",
          "sameDaySlots": 10,
          "nextDaySlots": 0,
          "nextAvailable": "Today \u2014 10 slots (next: 12:33)",
          "nextAvailableDate": "Today",
          "source": "corewellhealthurgentcarese.com",
          "lastChecked": "2026-04-16T12:30:50.073372",
          "address": "30955 Woodward Avenue Royal Oak, MI",
          "lat": 42.489,
          "lng": -83.144,
          "times": [
            "12:33",
            "12:37",
            "12:41",
            "12:45",
            "12:48",
            "12:52",
            "12:56",
            "01:00",
            "01:05",
            "01:10"
          ],
          "zip": "30955"
        },
        {
          "id": "cuc-6",
          "name": "Corewell UC \u2014 Chesterfield",
          "area": "Chesterfield",
          "type": "Urgent Care",
          "sameDaySlots": 10,
          "nextDaySlots": 0,
          "nextAvailable": "Today \u2014 10 slots (next: 12:36)",
          "nextAvailableDate": "Today",
          "source": "corewellhealthurgentcarese.com",
          "lastChecked": "2026-04-16T12:30:50.073436",
          "address": "50964 Gratiot Ave Chesterfield, MI",
          "lat": 42.673,
          "lng": -82.838,
          "times": [
            "12:36",
            "12:40",
            "12:43",
            "12:46",
            "12:50",
            "12:53",
            "12:56",
            "01:00",
            "01:03",
            "01:07"
          ],
          "zip": "50964"
        },
        {
          "id": "cuc-7",
          "name": "Corewell UC \u2014 Shelby Township",
          "area": "Shelby Township",
          "type": "Urgent Care",
          "sameDaySlots": 10,
          "nextDaySlots": 0,
          "nextAvailable": "Today \u2014 10 slots (next: 12:32)",
          "nextAvailableDate": "Today",
          "source": "corewellhealthurgentcarese.com",
          "lastChecked": "2026-04-16T12:30:50.073494",
          "address": "56293 Van Dyke Ave Shelby Township, MI",
          "lat": 42.671,
          "lng": -83.032,
          "times": [
            "12:32",
            "12:35",
            "12:38",
            "12:40",
            "12:43",
            "12:46",
            "12:49",
            "12:51",
            "12:54",
            "12:57"
          ],
          "zip": "56293"
        },
        {
          "id": "cuc-8",
          "name": "Corewell UC \u2014 Bloomfield Township",
          "area": "Bloomfield Township",
          "type": "Urgent Care",
          "sameDaySlots": 10,
          "nextDaySlots": 0,
          "nextAvailable": "Today \u2014 10 slots (next: 12:30)",
          "nextAvailableDate": "Today",
          "source": "corewellhealthurgentcarese.com",
          "lastChecked": "2026-04-16T12:30:50.073560",
          "address": "6543 Telegraph Road Bloomfield Township, MI",
          "lat": 42.583,
          "lng": -83.245,
          "times": [
            "12:30",
            "12:36",
            "12:40",
            "12:43",
            "12:46",
            "12:50",
            "12:53",
            "12:56",
            "01:00",
            "01:03"
          ],
          "zip": ""
        },
        {
          "id": "cuc-9",
          "name": "Corewell UC \u2014 Novi",
          "area": "Novi",
          "type": "Urgent Care",
          "sameDaySlots": 10,
          "nextDaySlots": 0,
          "nextAvailable": "Today \u2014 10 slots (next: 12:34)",
          "nextAvailableDate": "Today",
          "source": "corewellhealthurgentcarese.com",
          "lastChecked": "2026-04-16T12:30:50.073624",
          "address": "43535 Grand River Ave Novi, MI",
          "lat": 42.48,
          "lng": -83.476,
          "times": [
            "12:34",
            "12:38",
            "12:42",
            "12:47",
            "12:51",
            "12:55",
            "01:00",
            "01:05",
            "01:10",
            "01:15"
          ],
          "zip": "43535"
        },
        {
          "id": "cuc-0",
          "name": "Corewell UC \u2014 Southgate",
          "area": "Southgate",
          "type": "Urgent Care",
          "sameDaySlots": 10,
          "nextDaySlots": 0,
          "nextAvailable": "Today \u2014 10 slots (next: 12:30)",
          "nextAvailableDate": "Today",
          "source": "corewellhealthurgentcarese.com",
          "lastChecked": "2026-04-16T12:30:50.073690",
          "address": "16525 Fort Street Southgate, MI",
          "lat": 42.214,
          "lng": -83.194,
          "times": [
            "12:30",
            "12:34",
            "12:38",
            "12:42",
            "12:47",
            "12:51",
            "12:55",
            "01:00",
            "01:05",
            "01:10"
          ],
          "zip": "16525"
        },
        {
          "id": "cuc-1",
          "name": "Corewell UC \u2014 Warren West",
          "area": "Warren West",
          "type": "Urgent Care",
          "sameDaySlots": 10,
          "nextDaySlots": 0,
          "nextAvailable": "Today \u2014 10 slots (next: 12:30)",
          "nextAvailableDate": "Today",
          "source": "corewellhealthurgentcarese.com",
          "lastChecked": "2026-04-16T12:30:50.073751",
          "address": "28284 Dequindre Road Warren, MI",
          "lat": 42.49,
          "lng": -83.027,
          "times": [
            "12:30",
            "12:34",
            "12:38",
            "12:42",
            "12:47",
            "12:51",
            "12:55",
            "01:00",
            "01:05",
            "01:10"
          ],
          "zip": "28284"
        },
        {
          "id": "cuc-2",
          "name": "Corewell UC \u2014 Taylor",
          "area": "Taylor",
          "type": "Urgent Care",
          "sameDaySlots": 10,
          "nextDaySlots": 0,
          "nextAvailable": "Today \u2014 10 slots (next: 12:33)",
          "nextAvailableDate": "Today",
          "source": "corewellhealthurgentcarese.com",
          "lastChecked": "2026-04-16T12:30:50.073814",
          "address": "9870 Telegraph Road Taylor, MI",
          "lat": 42.241,
          "lng": -83.269,
          "times": [
            "12:33",
            "12:36",
            "12:40",
            "12:43",
            "12:46",
            "12:50",
            "12:53",
            "12:56",
            "01:00",
            "01:03"
          ],
          "zip": ""
        },
        {
          "id": "cuc-3",
          "name": "Corewell UC \u2014 Allen Park",
          "area": "Allen Park",
          "type": "Urgent Care",
          "sameDaySlots": 10,
          "nextDaySlots": 0,
          "nextAvailable": "Today \u2014 10 slots (next: 12:34)",
          "nextAvailableDate": "Today",
          "source": "corewellhealthurgentcarese.com",
          "lastChecked": "2026-04-16T12:30:50.073875",
          "address": "15606 Southfield Road Allen Park, MI",
          "lat": 42.473,
          "lng": -83.222,
          "times": [
            "12:34",
            "12:38",
            "12:47",
            "12:51",
            "12:55",
            "01:00",
            "01:10",
            "01:15",
            "01:20",
            "01:25"
          ],
          "zip": "15606"
        },
        {
          "id": "cuc-4",
          "name": "Corewell UC \u2014 Bloomfield Hills",
          "area": "Bloomfield Hills",
          "type": "Urgent Care",
          "sameDaySlots": 10,
          "nextDaySlots": 0,
          "nextAvailable": "Today \u2014 10 slots (next: 12:30)",
          "nextAvailableDate": "Today",
          "source": "corewellhealthurgentcarese.com",
          "lastChecked": "2026-04-16T12:30:50.073940",
          "address": "42757 Woodward Ave Bloomfield Hills, MI",
          "lat": 42.583,
          "lng": -83.245,
          "times": [
            "12:30",
            "12:34",
            "12:38",
            "12:42",
            "12:47",
            "12:51",
            "12:55",
            "01:00",
            "01:05",
            "01:10"
          ],
          "zip": "42757"
        },
        {
          "id": "cuc-5",
          "name": "Corewell UC \u2014 Warren East",
          "area": "Warren East",
          "type": "Urgent Care",
          "sameDaySlots": 10,
          "nextDaySlots": 0,
          "nextAvailable": "Today \u2014 10 slots (next: 12:30)",
          "nextAvailableDate": "Today",
          "source": "corewellhealthurgentcarese.com",
          "lastChecked": "2026-04-16T12:30:50.074002",
          "address": "28550 Schoenherr Road Warren, MI",
          "lat": 42.49,
          "lng": -83.027,
          "times": [
            "12:30",
            "12:34",
            "12:38",
            "12:42",
            "12:47",
            "12:51",
            "12:55",
            "01:00",
            "01:05",
            "01:10"
          ],
          "zip": "28550"
        },
        {
          "id": "cuc-6",
          "name": "Corewell UC \u2014 Grosse Pointe Farms",
          "area": "Grosse Pointe Farms",
          "type": "Urgent Care",
          "sameDaySlots": 10,
          "nextDaySlots": 0,
          "nextAvailable": "Today \u2014 10 slots (next: 12:33)",
          "nextAvailableDate": "Today",
          "source": "corewellhealthurgentcarese.com",
          "lastChecked": "2026-04-16T12:30:50.074059",
          "address": "18700 Mack Avenue Grosse Pointe Farms, MI",
          "lat": 42.387,
          "lng": -82.906,
          "times": [
            "12:33",
            "12:37",
            "12:41",
            "12:45",
            "12:48",
            "12:52",
            "12:56",
            "01:05",
            "01:10",
            "01:20"
          ],
          "zip": "18700"
        },
        {
          "id": "cuc-7",
          "name": "Corewell UC \u2014 Dearborn",
          "area": "Dearborn",
          "type": "Urgent Care",
          "sameDaySlots": 10,
          "nextDaySlots": 0,
          "nextAvailable": "Today \u2014 10 slots (next: 12:30)",
          "nextAvailableDate": "Today",
          "source": "corewellhealthurgentcarese.com",
          "lastChecked": "2026-04-16T12:30:50.074128",
          "address": "23100 Michigan Ave Dearborn, MI",
          "lat": 42.322,
          "lng": -83.176,
          "times": [
            "12:30",
            "12:33",
            "12:36",
            "12:40",
            "12:43",
            "12:46",
            "12:50",
            "12:53",
            "12:56",
            "01:00"
          ],
          "zip": "23100"
        },
        {
          "id": "cuc-8",
          "name": "Corewell UC \u2014 Haggerty Square",
          "area": "Haggerty Square",
          "type": "Urgent Care",
          "sameDaySlots": 10,
          "nextDaySlots": 0,
          "nextAvailable": "Today \u2014 10 slots (next: 12:33)",
          "nextAvailableDate": "Today",
          "source": "corewellhealthurgentcarese.com",
          "lastChecked": "2026-04-16T12:30:50.074189",
          "address": "19760 Haggerty Road Livonia, MI",
          "lat": 42.368,
          "lng": -83.353,
          "times": [
            "12:33",
            "12:36",
            "12:40",
            "12:43",
            "12:46",
            "12:50",
            "12:53",
            "12:56",
            "01:00",
            "01:03"
          ],
          "zip": "19760"
        },
        {
          "id": "cuc-9",
          "name": "Corewell UC \u2014 Downtown Royal Oak",
          "area": "Downtown Royal Oak",
          "type": "Urgent Care",
          "sameDaySlots": 10,
          "nextDaySlots": 0,
          "nextAvailable": "Today \u2014 10 slots (next: 12:37)",
          "nextAvailableDate": "Today",
          "source": "corewellhealthurgentcarese.com",
          "lastChecked": "2026-04-16T12:30:50.074251",
          "address": "309 E 11 Mile Road Royal Oak, MI",
          "lat": 42.489,
          "lng": -83.144,
          "times": [
            "12:37",
            "12:45",
            "12:52",
            "01:00",
            "01:10",
            "01:30",
            "02:00",
            "02:10",
            "02:20",
            "02:30"
          ],
          "zip": ""
        },
        {
          "id": "cuc-0",
          "name": "Corewell UC \u2014 Farmington Hills North",
          "area": "Farmington Hills North",
          "type": "Urgent Care",
          "sameDaySlots": 10,
          "nextDaySlots": 0,
          "nextAvailable": "Today \u2014 10 slots (next: 12:30)",
          "nextAvailableDate": "Today",
          "source": "corewellhealthurgentcarese.com",
          "lastChecked": "2026-04-16T12:30:50.074311",
          "address": "29263 Orchard Lake Road Farmington Hills, MI",
          "lat": 42.498,
          "lng": -83.377,
          "times": [
            "12:30",
            "12:34",
            "12:38",
            "12:42",
            "12:47",
            "12:51",
            "12:55",
            "01:00",
            "01:05",
            "01:10"
          ],
          "zip": "29263"
        },
        {
          "id": "cuc-1",
          "name": "Corewell UC \u2014 Wayne",
          "area": "Wayne",
          "type": "Urgent Care",
          "sameDaySlots": 10,
          "nextDaySlots": 0,
          "nextAvailable": "Today \u2014 10 slots (next: 12:33)",
          "nextAvailableDate": "Today",
          "source": "corewellhealthurgentcarese.com",
          "lastChecked": "2026-04-16T12:30:50.074371",
          "address": "34435 Michigan Avenue Wayne, MI",
          "lat": 42.282,
          "lng": -83.386,
          "times": [
            "12:33",
            "12:36",
            "12:40",
            "12:43",
            "12:46",
            "12:50",
            "12:53",
            "12:56",
            "01:00",
            "01:03"
          ],
          "zip": "34435"
        },
        {
          "id": "cuc-2",
          "name": "Corewell UC \u2014 Farmington Hills South",
          "area": "Farmington Hills South",
          "type": "Urgent Care",
          "sameDaySlots": 10,
          "nextDaySlots": 0,
          "nextAvailable": "Today \u2014 10 slots (next: 12:32)",
          "nextAvailableDate": "Today",
          "source": "corewellhealthurgentcarese.com",
          "lastChecked": "2026-04-16T12:30:50.074427",
          "address": "27810 Grand River Avenue Farmington Hills, MI",
          "lat": 42.498,
          "lng": -83.377,
          "times": [
            "12:32",
            "12:35",
            "12:38",
            "12:40",
            "12:43",
            "12:46",
            "12:49",
            "12:51",
            "12:54",
            "12:57"
          ],
          "zip": "27810"
        },
        {
          "id": "cuc-3",
          "name": "Corewell UC \u2014 Woodhaven",
          "area": "Woodhaven",
          "type": "Urgent Care",
          "sameDaySlots": 10,
          "nextDaySlots": 0,
          "nextAvailable": "Today \u2014 10 slots (next: 12:32)",
          "nextAvailableDate": "Today",
          "source": "corewellhealthurgentcarese.com",
          "lastChecked": "2026-04-16T12:30:50.074484",
          "address": "18930 West Road Woodhaven, MI",
          "lat": 42.139,
          "lng": -83.242,
          "times": [
            "12:32",
            "12:35",
            "12:38",
            "12:40",
            "12:43",
            "12:46",
            "12:49",
            "12:51",
            "12:54",
            "12:57"
          ],
          "zip": "18930"
        },
        {
          "id": "cuc-4",
          "name": "Corewell UC \u2014 Canton Michigan",
          "area": "Canton Michigan",
          "type": "Urgent Care",
          "sameDaySlots": 10,
          "nextDaySlots": 0,
          "nextAvailable": "Today \u2014 10 slots (next: 12:33)",
          "nextAvailableDate": "Today",
          "source": "corewellhealthurgentcarese.com",
          "lastChecked": "2026-04-16T12:30:50.074559",
          "address": "6549 N. Canton Center Road Canton, MI",
          "lat": 42.309,
          "lng": -83.482,
          "times": [
            "12:33",
            "12:36",
            "12:40",
            "12:43",
            "12:46",
            "12:50",
            "12:53",
            "12:56",
            "01:00",
            "01:03"
          ],
          "zip": ""
        },
        {
          "id": "cuc-5",
          "name": "Corewell UC \u2014 Troy Square Lake",
          "area": "Troy Square Lake",
          "type": "Urgent Care",
          "sameDaySlots": 10,
          "nextDaySlots": 0,
          "nextAvailable": "Today \u2014 10 slots (next: 12:32)",
          "nextAvailableDate": "Today",
          "source": "corewellhealthurgentcarese.com",
          "lastChecked": "2026-04-16T12:30:50.074621",
          "address": "43037 Dequindre Road Troy, MI",
          "lat": 42.606,
          "lng": -83.15,
          "times": [
            "12:32",
            "12:35",
            "12:38",
            "12:40",
            "12:43",
            "12:46",
            "12:49",
            "12:51",
            "12:54",
            "12:57"
          ],
          "zip": "43037"
        },
        {
          "id": "cuc-6",
          "name": "Corewell UC \u2014 West Bloomfield",
          "area": "West Bloomfield",
          "type": "Urgent Care",
          "sameDaySlots": 10,
          "nextDaySlots": 0,
          "nextAvailable": "Today \u2014 10 slots (next: 12:34)",
          "nextAvailableDate": "Today",
          "source": "corewellhealthurgentcarese.com",
          "lastChecked": "2026-04-16T12:30:50.074680",
          "address": "6470 Orchard Lake Road West Bloomfield, MI",
          "lat": 42.565,
          "lng": -83.382,
          "times": [
            "12:34",
            "12:38",
            "12:42",
            "12:47",
            "12:51",
            "12:55",
            "01:00",
            "01:05",
            "01:10",
            "01:15"
          ],
          "zip": ""
        },
        {
          "id": "cuc-7",
          "name": "Corewell UC \u2014 St Clair Shores",
          "area": "St Clair Shores",
          "type": "Urgent Care",
          "sameDaySlots": 10,
          "nextDaySlots": 0,
          "nextAvailable": "Today \u2014 10 slots (next: 12:32)",
          "nextAvailableDate": "Today",
          "source": "corewellhealthurgentcarese.com",
          "lastChecked": "2026-04-16T12:30:50.074736",
          "address": "25631 Little Mack Avenue St Clair Shores, MI",
          "lat": 42.497,
          "lng": -82.891,
          "times": [
            "12:32",
            "12:35",
            "12:37",
            "12:40",
            "12:42",
            "12:45",
            "12:47",
            "12:50",
            "12:52",
            "12:55"
          ],
          "zip": "25631"
        },
        {
          "id": "cuc-8",
          "name": "Corewell UC \u2014 Garden City",
          "area": "Garden City",
          "type": "Urgent Care",
          "sameDaySlots": 10,
          "nextDaySlots": 0,
          "nextAvailable": "Today \u2014 10 slots (next: 12:33)",
          "nextAvailableDate": "Today",
          "source": "corewellhealthurgentcarese.com",
          "lastChecked": "2026-04-16T12:30:50.074805",
          "address": "6200 Middlebelt Road Garden City, MI",
          "lat": 42.326,
          "lng": -83.331,
          "times": [
            "12:33",
            "12:36",
            "12:40",
            "12:43",
            "12:46",
            "12:50",
            "12:53",
            "12:56",
            "01:00",
            "01:03"
          ],
          "zip": ""
        }
      ]
    },
    "doctors_care": {
      "name": "Doctors Urgent Care",
      "locations": [
        {
          "id": "dc-65575",
          "name": "Doctors Care \u2014 Redford",
          "area": "Redford",
          "type": "Urgent Care",
          "sameDaySlots": 0,
          "nextDaySlots": 0,
          "nextAvailable": "Walk-in (no online slots)",
          "nextAvailableDate": "",
          "source": "AdvancedMD",
          "lastChecked": "2026-03-25T13:45:17.278978",
          "address": "14671 Telegraph Rd, Redford, MI 48239",
          "lat": 42.385,
          "lng": -83.297
        },
        {
          "id": "dc-10626",
          "name": "Doctors Care \u2014 Canton",
          "area": "Canton",
          "type": "Urgent Care",
          "sameDaySlots": 0,
          "nextDaySlots": 0,
          "nextAvailable": "Walk-in (no online slots)",
          "nextAvailableDate": "",
          "source": "AdvancedMD",
          "lastChecked": "2026-03-25T13:45:17.284041",
          "address": "43033 Ford Rd, Canton, MI 48187",
          "lat": 42.309,
          "lng": -83.482
        },
        {
          "id": "dc-1854",
          "name": "Doctors Care \u2014 Commerce",
          "area": "Commerce",
          "type": "Urgent Care",
          "sameDaySlots": 0,
          "nextDaySlots": 0,
          "nextAvailable": "Walk-in (no online slots)",
          "nextAvailableDate": "",
          "source": "AdvancedMD",
          "lastChecked": "2026-03-25T13:45:17.286721",
          "address": "2900 Union Lake Rd, Commerce, MI 48382",
          "lat": 42.56,
          "lng": -83.49
        },
        {
          "id": "dc-40184",
          "name": "Doctors Care \u2014 Chesterfield",
          "area": "Chesterfield",
          "type": "Urgent Care",
          "sameDaySlots": 0,
          "nextDaySlots": 0,
          "nextAvailable": "Walk-in (no online slots)",
          "nextAvailableDate": "",
          "source": "AdvancedMD",
          "lastChecked": "2026-03-25T13:45:17.289506",
          "address": "51160 Gratiot Ave, Chesterfield, MI 48051",
          "lat": 42.673,
          "lng": -82.838
        },
        {
          "id": "dc-41393",
          "name": "Doctors Care \u2014 Clinton Township",
          "area": "Clinton Township",
          "type": "Urgent Care",
          "sameDaySlots": 0,
          "nextDaySlots": 0,
          "nextAvailable": "Walk-in (no online slots)",
          "nextAvailableDate": "",
          "source": "AdvancedMD",
          "lastChecked": "2026-03-25T13:45:17.293415",
          "address": "37150 S Gratiot Ave, Clinton Township, MI 48036",
          "lat": 42.582,
          "lng": -82.929
        },
        {
          "id": "dc-37083",
          "name": "Doctors Care \u2014 Shelby",
          "area": "Shelby",
          "type": "Urgent Care",
          "sameDaySlots": 0,
          "nextDaySlots": 0,
          "nextAvailable": "Walk-in (no online slots)",
          "nextAvailableDate": "",
          "source": "AdvancedMD",
          "lastChecked": "2026-03-25T13:45:17.296593",
          "address": "46961 Van Dyke Ave, Shelby Township, MI 48317",
          "lat": 42.671,
          "lng": -83.032
        },
        {
          "id": "dc-36632",
          "name": "Doctors Care \u2014 Livonia",
          "area": "Livonia",
          "type": "Urgent Care",
          "sameDaySlots": 0,
          "nextDaySlots": 0,
          "nextAvailable": "Walk-in (no online slots)",
          "nextAvailableDate": "",
          "source": "AdvancedMD",
          "lastChecked": "2026-03-25T13:45:17.300583",
          "address": "36700 Five Mile Rd, Livonia, MI 48154",
          "lat": 42.368,
          "lng": -83.353
        },
        {
          "id": "dc-63869",
          "name": "Doctors Care \u2014 Farmington Hills",
          "area": "Farmington Hills",
          "type": "Urgent Care",
          "sameDaySlots": 0,
          "nextDaySlots": 0,
          "nextAvailable": "Walk-in (no online slots)",
          "nextAvailableDate": "",
          "source": "AdvancedMD",
          "lastChecked": "2026-03-25T13:45:17.303474",
          "address": "25950 Middlebelt Rd, Farmington Hills, MI 48336",
          "lat": 42.498,
          "lng": -83.377
        },
        {
          "id": "dc-56880",
          "name": "Doctors Care \u2014 Lambertville",
          "area": "Lambertville",
          "type": "Urgent Care",
          "sameDaySlots": 0,
          "nextDaySlots": 0,
          "nextAvailable": "Walk-in (no online slots)",
          "nextAvailableDate": "",
          "source": "AdvancedMD",
          "lastChecked": "2026-03-25T13:45:17.308392",
          "address": "3299 Sterns Rd, Lambertville, MI 48144",
          "lat": null,
          "lng": null
        },
        {
          "id": "dc-63872",
          "name": "Doctors Care \u2014 Adrian",
          "area": "Adrian",
          "type": "Urgent Care",
          "sameDaySlots": 0,
          "nextDaySlots": 0,
          "nextAvailable": "Walk-in (no online slots)",
          "nextAvailableDate": "",
          "source": "AdvancedMD",
          "lastChecked": "2026-03-25T13:45:17.316686",
          "address": "905 N Main St Suite 2, Adrian, MI 49221",
          "lat": null,
          "lng": null
        },
        {
          "id": "dc-33328",
          "name": "Doctors Care \u2014 Plainwell",
          "area": "Plainwell",
          "type": "Urgent Care",
          "sameDaySlots": 0,
          "nextDaySlots": 0,
          "nextAvailable": "Walk-in (no online slots)",
          "nextAvailableDate": "",
          "source": "AdvancedMD",
          "lastChecked": "2026-03-25T13:45:17.326343",
          "address": "1221 M-89 Suite 200, Plainwell, MI 49080",
          "lat": null,
          "lng": null
        },
        {
          "id": "dc-16805",
          "name": "Doctors Care \u2014 Rochester Hills",
          "area": "Rochester Hills",
          "type": "Urgent Care",
          "sameDaySlots": 0,
          "nextDaySlots": 0,
          "nextAvailable": "Walk-in (no online slots)",
          "nextAvailableDate": "",
          "source": "AdvancedMD",
          "lastChecked": "2026-03-25T13:45:17.336147",
          "address": "2915 Walton Blvd, Rochester Hills, MI 48309",
          "lat": 42.65,
          "lng": -83.15
        },
        {
          "id": "dc-38190",
          "name": "Doctors Care \u2014 Taylor",
          "area": "Taylor",
          "type": "Urgent Care",
          "sameDaySlots": 0,
          "nextDaySlots": 0,
          "nextAvailable": "Walk-in (no online slots)",
          "nextAvailableDate": "",
          "source": "AdvancedMD",
          "lastChecked": "2026-03-25T13:45:17.345000",
          "address": "23234 Ecorse Rd, Taylor, MI 48180",
          "lat": 42.241,
          "lng": -83.269
        },
        {
          "id": "dc-68985",
          "name": "Doctors Care \u2014 Troy",
          "area": "Troy",
          "type": "Urgent Care",
          "sameDaySlots": 0,
          "nextDaySlots": 0,
          "nextAvailable": "Walk-in (no online slots)",
          "nextAvailableDate": "",
          "source": "AdvancedMD",
          "lastChecked": "2026-03-25T13:45:17.352460",
          "address": "4060 Rochester Rd, Troy, MI 48085",
          "lat": 42.6,
          "lng": -83.12
        },
        {
          "id": "dc-89184",
          "name": "Doctors Care \u2014 Tecumseh",
          "area": "Tecumseh",
          "type": "Urgent Care",
          "sameDaySlots": 0,
          "nextDaySlots": 0,
          "nextAvailable": "Walk-in (no online slots)",
          "nextAvailableDate": "",
          "source": "AdvancedMD",
          "lastChecked": "2026-03-25T13:45:17.359718",
          "address": "501 E Chicago Blvd, Tecumseh, MI 49286",
          "lat": null,
          "lng": null
        },
        {
          "id": "dc-68621",
          "name": "Doctors Care \u2014 Ypsilanti",
          "area": "Ypsilanti",
          "type": "Urgent Care",
          "sameDaySlots": 0,
          "nextDaySlots": 0,
          "nextAvailable": "Walk-in (no online slots)",
          "nextAvailableDate": "",
          "source": "AdvancedMD",
          "lastChecked": "2026-03-25T13:45:17.367202",
          "address": "301 W Michigan Ave Ste 100, Ypsilanti, MI 48197",
          "lat": 42.22,
          "lng": -83.62
        }
      ]
    }
  },
  "errors": []
}