{
  "lastUpdated": "2026-04-14T12:03:22",
  "market": "Michigan",
  "systems": {
    "gohealth_uc": {
      "name": "GoHealth / Henry Ford UC",
      "locations": [
        {
          "id": "gh-49656",
          "name": "GoHealth UC \u2014 Berkley",
          "area": "Berkley",
          "type": "Urgent Care",
          "sameDaySlots": 27,
          "nextDaySlots": 0,
          "nextAvailable": "Tue 4/14 \u2014 27 slots (first: 12:12 PM)",
          "nextAvailableDate": "Tue 4/14",
          "source": "GoHealth",
          "lastChecked": "2026-04-14T12:03:48.174754",
          "address": "2695 Coolidge Hwy, Berkley, MI 48072",
          "lat": 42.5,
          "lng": -83.184
        },
        {
          "id": "gh-80237",
          "name": "GoHealth UC \u2014 Bruce Township",
          "area": "Bruce Township",
          "type": "Urgent Care",
          "sameDaySlots": 28,
          "nextDaySlots": 0,
          "nextAvailable": "Tue 4/14 \u2014 28 slots (first: 12:19 PM)",
          "nextAvailableDate": "Tue 4/14",
          "source": "GoHealth",
          "lastChecked": "2026-04-14T12:04:08.388460",
          "address": "71050 Van Dyke Rd, Bruce Township, MI 48065",
          "lat": 42.818,
          "lng": -83.019
        },
        {
          "id": "gh-51912",
          "name": "GoHealth UC \u2014 Canton",
          "area": "Canton",
          "type": "Urgent Care",
          "sameDaySlots": 29,
          "nextDaySlots": 0,
          "nextAvailable": "Tue 4/14 \u2014 29 slots (first: 12:19 PM)",
          "nextAvailableDate": "Tue 4/14",
          "source": "GoHealth",
          "lastChecked": "2026-04-14T12:04:28.344179",
          "address": "43821 Ford Rd, Canton, MI 48187",
          "lat": 42.322,
          "lng": -83.475
        },
        {
          "id": "gh-23051",
          "name": "GoHealth UC \u2014 Chesterfield",
          "area": "Chesterfield",
          "type": "Urgent Care",
          "sameDaySlots": 27,
          "nextDaySlots": 0,
          "nextAvailable": "Tue 4/14 \u2014 27 slots (first: 12:30 PM)",
          "nextAvailableDate": "Tue 4/14",
          "source": "GoHealth",
          "lastChecked": "2026-04-14T12:04:48.427996",
          "address": "50637 Gratiot Ave, Chesterfield, MI 48051",
          "lat": 42.673,
          "lng": -82.838
        },
        {
          "id": "gh-96311",
          "name": "GoHealth UC \u2014 Clinton Township",
          "area": "Clinton Township",
          "type": "Urgent Care",
          "sameDaySlots": 29,
          "nextDaySlots": 0,
          "nextAvailable": "Tue 4/14 \u2014 29 slots (first: 12:20 PM)",
          "nextAvailableDate": "Tue 4/14",
          "source": "GoHealth",
          "lastChecked": "2026-04-14T12:05:08.364918",
          "address": "42010 Garfield Rd, Clinton Township, MI 48038",
          "lat": 42.582,
          "lng": -82.929
        },
        {
          "id": "gh-11360",
          "name": "GoHealth UC \u2014 Commerce Township",
          "area": "Commerce Township",
          "type": "Urgent Care",
          "sameDaySlots": 28,
          "nextDaySlots": 0,
          "nextAvailable": "Tue 4/14 \u2014 28 slots (first: 12:44 PM)",
          "nextAvailableDate": "Tue 4/14",
          "source": "GoHealth",
          "lastChecked": "2026-04-14T12:05:28.243532",
          "address": "3030 Union Lake Rd, Commerce Township, MI 48382",
          "lat": 42.568,
          "lng": -83.494
        },
        {
          "id": "gh-30767",
          "name": "GoHealth UC \u2014 Dearborn Heights",
          "area": "Dearborn Heights",
          "type": "Urgent Care",
          "sameDaySlots": 27,
          "nextDaySlots": 0,
          "nextAvailable": "Tue 4/14 \u2014 27 slots (first: 12:40 PM)",
          "nextAvailableDate": "Tue 4/14",
          "source": "GoHealth",
          "lastChecked": "2026-04-14T12:05:48.796468",
          "address": "25520 Ford Rd, Dearborn Heights, MI 48127",
          "lat": 42.337,
          "lng": -83.273
        },
        {
          "id": "gh-80954",
          "name": "GoHealth UC \u2014 Fraser",
          "area": "Fraser",
          "type": "Urgent Care",
          "sameDaySlots": 25,
          "nextDaySlots": 0,
          "nextAvailable": "Tue 4/14 \u2014 25 slots (first: 12:08 PM)",
          "nextAvailableDate": "Tue 4/14",
          "source": "GoHealth",
          "lastChecked": "2026-04-14T12:06:08.871328",
          "address": "33730 Garfield Rd, Fraser, MI 48026",
          "lat": 42.539,
          "lng": -82.949
        },
        {
          "id": "gh-20810",
          "name": "GoHealth UC \u2014 Livonia",
          "area": "Livonia",
          "type": "Urgent Care",
          "sameDaySlots": 26,
          "nextDaySlots": 0,
          "nextAvailable": "Tue 4/14 \u2014 26 slots (first: 12:21 PM)",
          "nextAvailableDate": "Tue 4/14",
          "source": "GoHealth",
          "lastChecked": "2026-04-14T12:06:28.958133",
          "address": "37672 Seven Mile Rd, Livonia, MI 48152",
          "lat": 42.4,
          "lng": -83.38
        },
        {
          "id": "gh-84227",
          "name": "GoHealth UC \u2014 Southfield",
          "area": "Southfield",
          "type": "Urgent Care",
          "sameDaySlots": 25,
          "nextDaySlots": 0,
          "nextAvailable": "Tue 4/14 \u2014 25 slots (first: 12:35 PM)",
          "nextAvailableDate": "Tue 4/14",
          "source": "GoHealth",
          "lastChecked": "2026-04-14T12:06:49.087344",
          "address": "29305 Southfield Rd, Southfield, MI 48076",
          "lat": 42.473,
          "lng": -83.222
        },
        {
          "id": "gh-6093",
          "name": "GoHealth UC \u2014 Southgate",
          "area": "Southgate",
          "type": "Urgent Care",
          "sameDaySlots": 29,
          "nextDaySlots": 0,
          "nextAvailable": "Tue 4/14 \u2014 29 slots (first: 12:22 PM)",
          "nextAvailableDate": "Tue 4/14",
          "source": "GoHealth",
          "lastChecked": "2026-04-14T12:07:09.067275",
          "address": "14750 Dix Toledo Rd, Southgate, MI 48195",
          "lat": 42.214,
          "lng": -83.194
        },
        {
          "id": "gh-30181",
          "name": "GoHealth UC \u2014 St. Clair Shores",
          "area": "St. Clair Shores",
          "type": "Urgent Care",
          "sameDaySlots": 29,
          "nextDaySlots": 0,
          "nextAvailable": "Tue 4/14 \u2014 29 slots (first: 12:13 PM)",
          "nextAvailableDate": "Tue 4/14",
          "source": "GoHealth",
          "lastChecked": "2026-04-14T12:07:28.855246",
          "address": "21950 Harper Ave, St. Clair Shores, MI 48080",
          "lat": 42.497,
          "lng": -82.891
        },
        {
          "id": "gh-4626",
          "name": "GoHealth UC \u2014 Taylor",
          "area": "Taylor",
          "type": "Urgent Care",
          "sameDaySlots": 29,
          "nextDaySlots": 0,
          "nextAvailable": "Tue 4/14 \u2014 29 slots (first: 12:22 PM)",
          "nextAvailableDate": "Tue 4/14",
          "source": "GoHealth",
          "lastChecked": "2026-04-14T12:07:48.878247",
          "address": "22395 Ecorse Rd, Taylor, MI 48180",
          "lat": 42.241,
          "lng": -83.269
        },
        {
          "id": "gh-77292",
          "name": "GoHealth UC \u2014 West Bloomfield",
          "area": "West Bloomfield",
          "type": "Urgent Care",
          "sameDaySlots": 26,
          "nextDaySlots": 0,
          "nextAvailable": "Tue 4/14 \u2014 26 slots (first: 12:23 PM)",
          "nextAvailableDate": "Tue 4/14",
          "source": "GoHealth",
          "lastChecked": "2026-04-14T12:08:08.878690",
          "address": "6555 Orchard Lake Rd, West Bloomfield, MI 48322",
          "lat": 42.565,
          "lng": -83.382
        },
        {
          "id": "gh-46203",
          "name": "GoHealth UC \u2014 Wonderland Village Livonia",
          "area": "Wonderland Village Livonia",
          "type": "Urgent Care",
          "sameDaySlots": 26,
          "nextDaySlots": 0,
          "nextAvailable": "Tue 4/14 \u2014 26 slots (first: 12:36 PM)",
          "nextAvailableDate": "Tue 4/14",
          "source": "GoHealth",
          "lastChecked": "2026-04-14T12:08:28.613796",
          "address": "29321 Plymouth Rd, Livonia, MI 48150",
          "lat": 42.368,
          "lng": -83.353
        }
      ]
    },
    "firstchoice_uc": {
      "name": "1st Choice Urgent Care",
      "locations": [
        {
          "id": "fc-64718",
          "name": "1st Choice UC \u2014 Bloomfield",
          "area": "Bloomfield",
          "type": "Urgent Care",
          "sameDaySlots": 28,
          "nextDaySlots": 0,
          "nextAvailable": "Tue 4/14 \u2014 28 slots (first: 12:07 pm)",
          "nextAvailableDate": "Tue 4/14",
          "source": "Solv",
          "lastChecked": "2026-04-14T12:00:10.113316",
          "address": "2274 S Telegraph Rd, Bloomfield, MI 48302",
          "lat": 42.61,
          "lng": -83.28
        },
        {
          "id": "fc-78346",
          "name": "1st Choice UC \u2014 Clinton Township",
          "area": "Clinton Township",
          "type": "Urgent Care",
          "sameDaySlots": 28,
          "nextDaySlots": 0,
          "nextAvailable": "Tue 4/14 \u2014 28 slots (first: 1:10 pm)",
          "nextAvailableDate": "Tue 4/14",
          "source": "Solv",
          "lastChecked": "2026-04-14T12:00:23.663997",
          "address": "44472 Hayes Rd, Clinton Township, MI 48038",
          "lat": 42.582,
          "lng": -82.929
        },
        {
          "id": "fc-62790",
          "name": "1st Choice UC \u2014 Dearborn East",
          "area": "Dearborn East",
          "type": "Urgent Care",
          "sameDaySlots": 28,
          "nextDaySlots": 0,
          "nextAvailable": "Tue 4/14 \u2014 28 slots (first: 12:10 pm)",
          "nextAvailableDate": "Tue 4/14",
          "source": "Solv",
          "lastChecked": "2026-04-14T12:00:35.348609",
          "address": "12841 Ford Rd, Dearborn, MI 48126",
          "lat": 42.322,
          "lng": -83.176
        },
        {
          "id": "fc-55855",
          "name": "1st Choice UC \u2014 Dearborn West",
          "area": "Dearborn West",
          "type": "Urgent Care",
          "sameDaySlots": 28,
          "nextDaySlots": 0,
          "nextAvailable": "Tue 4/14 \u2014 28 slots (first: 12:10 pm)",
          "nextAvailableDate": "Tue 4/14",
          "source": "Solv",
          "lastChecked": "2026-04-14T12:00:45.945361",
          "address": "23455 Michigan Ave, Dearborn, MI 48124",
          "lat": 42.322,
          "lng": -83.176
        },
        {
          "id": "fc-45958",
          "name": "1st Choice UC \u2014 Garden City",
          "area": "Garden City",
          "type": "Urgent Care",
          "sameDaySlots": 28,
          "nextDaySlots": 0,
          "nextAvailable": "Tue 4/14 \u2014 28 slots (first: 12:10 pm)",
          "nextAvailableDate": "Tue 4/14",
          "source": "Solv",
          "lastChecked": "2026-04-14T12:00:56.521626",
          "address": "31450 Ford Rd, Garden City, MI 48135",
          "lat": 42.326,
          "lng": -83.331
        },
        {
          "id": "fc-80481",
          "name": "1st Choice UC \u2014 Livonia",
          "area": "Livonia",
          "type": "Urgent Care",
          "sameDaySlots": 28,
          "nextDaySlots": 0,
          "nextAvailable": "Tue 4/14 \u2014 28 slots (first: 12:05 pm)",
          "nextAvailableDate": "Tue 4/14",
          "source": "Solv",
          "lastChecked": "2026-04-14T12:01:07.701930",
          "address": "11502 Middlebelt Rd, Livonia, MI 48150",
          "lat": 42.368,
          "lng": -83.353
        },
        {
          "id": "fc-97179",
          "name": "1st Choice UC \u2014 Macomb",
          "area": "Macomb",
          "type": "Urgent Care",
          "sameDaySlots": 28,
          "nextDaySlots": 0,
          "nextAvailable": "Tue 4/14 \u2014 28 slots (first: 1:10 pm)",
          "nextAvailableDate": "Tue 4/14",
          "source": "Solv",
          "lastChecked": "2026-04-14T12:01:18.641274",
          "address": "18200 23 Mile Rd, Macomb, MI 48044",
          "lat": 42.672,
          "lng": -82.912
        },
        {
          "id": "fc-51519",
          "name": "1st Choice UC \u2014 Oxford",
          "area": "Oxford",
          "type": "Urgent Care",
          "sameDaySlots": 28,
          "nextDaySlots": 0,
          "nextAvailable": "Tue 4/14 \u2014 28 slots (first: 1:10 pm)",
          "nextAvailableDate": "Tue 4/14",
          "source": "Solv",
          "lastChecked": "2026-04-14T12:01:29.853265",
          "address": "72 S Washington St Suite 102, Oxford, MI 48371",
          "lat": 42.82,
          "lng": -83.27
        },
        {
          "id": "fc-5356",
          "name": "1st Choice UC \u2014 Rochester Hills",
          "area": "Rochester Hills",
          "type": "Urgent Care",
          "sameDaySlots": 28,
          "nextDaySlots": 0,
          "nextAvailable": "Tue 4/14 \u2014 28 slots (first: 1:10 pm)",
          "nextAvailableDate": "Tue 4/14",
          "source": "Solv",
          "lastChecked": "2026-04-14T12:01:41.326682",
          "address": "2952 S Rochester Rd, Rochester Hills, MI 48307",
          "lat": 42.67,
          "lng": -83.14
        },
        {
          "id": "fc-32927",
          "name": "1st Choice UC \u2014 Romulus",
          "area": "Romulus",
          "type": "Urgent Care",
          "sameDaySlots": 28,
          "nextDaySlots": 0,
          "nextAvailable": "Tue 4/14 \u2014 28 slots (first: 1:10 pm)",
          "nextAvailableDate": "Tue 4/14",
          "source": "Solv",
          "lastChecked": "2026-04-14T12:01:52.695646",
          "address": "29750 Ecorse Rd, Romulus, MI 48174",
          "lat": 42.222,
          "lng": -83.393
        },
        {
          "id": "fc-87033",
          "name": "1st Choice UC \u2014 Royal Oak",
          "area": "Royal Oak",
          "type": "Urgent Care",
          "sameDaySlots": 28,
          "nextDaySlots": 0,
          "nextAvailable": "Tue 4/14 \u2014 28 slots (first: 1:10 pm)",
          "nextAvailableDate": "Tue 4/14",
          "source": "Solv",
          "lastChecked": "2026-04-14T12:02:02.951374",
          "address": "4080 Crooks Rd, Royal Oak, MI 48073",
          "lat": 42.52,
          "lng": -83.16
        },
        {
          "id": "fc-20969",
          "name": "1st Choice UC \u2014 Saint Clair Shores",
          "area": "Saint Clair Shores",
          "type": "Urgent Care",
          "sameDaySlots": 28,
          "nextDaySlots": 0,
          "nextAvailable": "Tue 4/14 \u2014 28 slots (first: 1:10 pm)",
          "nextAvailableDate": "Tue 4/14",
          "source": "Solv",
          "lastChecked": "2026-04-14T12:02:13.280574",
          "address": "25515 Harper Ave, Saint Clair Shores, MI 48081",
          "lat": 42.497,
          "lng": -82.891
        },
        {
          "id": "fc-56458",
          "name": "1st Choice UC \u2014 Southfield",
          "area": "Southfield",
          "type": "Urgent Care",
          "sameDaySlots": 28,
          "nextDaySlots": 0,
          "nextAvailable": "Tue 4/14 \u2014 28 slots (first: 12:07 pm)",
          "nextAvailableDate": "Tue 4/14",
          "source": "Solv",
          "lastChecked": "2026-04-14T12:02:24.633124",
          "address": "29628 Southfield Rd, Southfield, MI 48076",
          "lat": 42.473,
          "lng": -83.222
        },
        {
          "id": "fc-11740",
          "name": "1st Choice UC \u2014 Taylor",
          "area": "Taylor",
          "type": "Urgent Care",
          "sameDaySlots": 14,
          "nextDaySlots": 0,
          "nextAvailable": "Tue 4/14 \u2014 14 slots (first: 12:10 pm)",
          "nextAvailableDate": "Tue 4/14",
          "source": "Solv",
          "lastChecked": "2026-04-14T12:02:35.292883",
          "address": "10155 Telegraph Rd, Taylor, MI 48180",
          "lat": 42.241,
          "lng": -83.269
        },
        {
          "id": "fc-29030",
          "name": "1st Choice UC \u2014 Warren",
          "area": "Warren",
          "type": "Urgent Care",
          "sameDaySlots": 28,
          "nextDaySlots": 0,
          "nextAvailable": "Tue 4/14 \u2014 28 slots (first: 12:10 pm)",
          "nextAvailableDate": "Tue 4/14",
          "source": "Solv",
          "lastChecked": "2026-04-14T12:02:46.800255",
          "address": "25600 Schoenherr Rd, Warren, MI 48089",
          "lat": 42.49,
          "lng": -83.027
        },
        {
          "id": "fc-2462",
          "name": "1st Choice UC \u2014 Washington",
          "area": "Washington",
          "type": "Urgent Care",
          "sameDaySlots": 28,
          "nextDaySlots": 0,
          "nextAvailable": "Tue 4/14 \u2014 28 slots (first: 1:10 pm)",
          "nextAvailableDate": "Tue 4/14",
          "source": "Solv",
          "lastChecked": "2026-04-14T12:02:58.012282",
          "address": "7701 26 Mile Rd, Washington, MI 48094",
          "lat": 42.736,
          "lng": -83.035
        },
        {
          "id": "fc-67138",
          "name": "1st Choice UC \u2014 Waterford",
          "area": "Waterford",
          "type": "Urgent Care",
          "sameDaySlots": 28,
          "nextDaySlots": 0,
          "nextAvailable": "Tue 4/14 \u2014 28 slots (first: 1:10 pm)",
          "nextAvailableDate": "Tue 4/14",
          "source": "Solv",
          "lastChecked": "2026-04-14T12:03:09.289645",
          "address": "2446 Elizabeth Lake, Waterford, MI 48328",
          "lat": 42.62,
          "lng": -83.38
        },
        {
          "id": "fc-90231",
          "name": "1st Choice UC \u2014 Ypsilanti",
          "area": "Ypsilanti",
          "type": "Urgent Care",
          "sameDaySlots": 28,
          "nextDaySlots": 0,
          "nextAvailable": "Tue 4/14 \u2014 28 slots (first: 1:10 pm)",
          "nextAvailableDate": "Tue 4/14",
          "source": "Solv",
          "lastChecked": "2026-04-14T12:03:21.009787",
          "address": "494 N Hewitt Rd, Ypsilanti, MI 48197",
          "lat": 42.22,
          "lng": -83.62
        }
      ]
    },
    "corewell_pc": {
      "name": "Corewell Health Primary Care",
      "locations": [
        {
          "id": "cpc-14117",
          "name": "Corewell Health Internal Medicine",
          "area": "Troy",
          "type": "Primary Care",
          "sameDaySlots": 0,
          "nextDaySlots": 1,
          "nextAvailable": "Wed 4/15 \u2014 1 slots (first: 11:00 AM)",
          "nextAvailableDate": "Wed 4/15",
          "source": "MyChart",
          "lastChecked": "2026-04-14T11:59:53.361277",
          "address": "38865 Dequindre Rd Ste 106 Troy MI 48083-6812",
          "lat": 42.606,
          "lng": -83.15
        },
        {
          "id": "cpc-27963",
          "name": "Corewell Health Primary Care",
          "area": "Mile Rd Saint Clair Shores",
          "type": "Primary Care",
          "sameDaySlots": 0,
          "nextDaySlots": 5,
          "nextAvailable": "Wed 4/15 \u2014 5 slots (first: 8:00 AM)",
          "nextAvailableDate": "Wed 4/15",
          "source": "MyChart",
          "lastChecked": "2026-04-14T11:59:53.361404",
          "address": "21400 E 11 Mile Rd Saint Clair Shores MI 48081-1566",
          "lat": 42.497,
          "lng": -82.891
        },
        {
          "id": "cpc-19093",
          "name": "Corewell Health Internal Medicine",
          "area": "Roseville",
          "type": "Primary Care",
          "sameDaySlots": 0,
          "nextDaySlots": 8,
          "nextAvailable": "Wed 4/15 \u2014 8 slots (first: 12:00 PM)",
          "nextAvailableDate": "Wed 4/15",
          "source": "MyChart",
          "lastChecked": "2026-04-14T11:59:53.361498",
          "address": "18325 E 10 Mile Rd Ste 300 Roseville MI 48066-4990",
          "lat": 42.497,
          "lng": -82.937
        },
        {
          "id": "cpc-62646",
          "name": "Corewell Health Family Medicine",
          "area": "Roseville",
          "type": "Primary Care",
          "sameDaySlots": 0,
          "nextDaySlots": 2,
          "nextAvailable": "Wed 4/15 \u2014 2 slots (first: 7:00 AM)",
          "nextAvailableDate": "Wed 4/15",
          "source": "MyChart",
          "lastChecked": "2026-04-14T11:59:53.361573",
          "address": "30695 Little Mack Ave Ste 200 Roseville MI 48066-1781",
          "lat": 42.497,
          "lng": -82.937
        },
        {
          "id": "cpc-51869",
          "name": "Corewell Health Family Medicine",
          "area": "Royal Oak",
          "type": "Primary Care",
          "sameDaySlots": 0,
          "nextDaySlots": 3,
          "nextAvailable": "Wed 4/15 \u2014 3 slots (first: 11:00 AM)",
          "nextAvailableDate": "Wed 4/15",
          "source": "MyChart",
          "lastChecked": "2026-04-14T11:59:53.361681",
          "address": "309 E 11 Mile Rd Ste B Royal Oak MI 48067-2735",
          "lat": 42.49,
          "lng": -83.14
        },
        {
          "id": "cpc-89713",
          "name": "Corewell Health Family Medicine - Livonia/Northville",
          "area": "Livonia",
          "type": "Primary Care",
          "sameDaySlots": 0,
          "nextDaySlots": 0,
          "nextAvailable": "Fri 4/17 \u2014 15 slots (first: 1:00 PM)",
          "nextAvailableDate": "Fri 4/17",
          "source": "MyChart",
          "lastChecked": "2026-04-14T11:59:53.361756",
          "address": "39000 7 Mile Rd Ste 4300 Livonia MI 48152-1006",
          "lat": 42.368,
          "lng": -83.353
        },
        {
          "id": "cpc-93558",
          "name": "Corewell Health Family Medicine",
          "area": "Dix Toledo Rd Southgate",
          "type": "Primary Care",
          "sameDaySlots": 0,
          "nextDaySlots": 0,
          "nextAvailable": "Fri 4/17 \u2014 14 slots (first: 9:30 AM)",
          "nextAvailableDate": "Fri 4/17",
          "source": "MyChart",
          "lastChecked": "2026-04-14T11:59:53.361819",
          "address": "14319 Dix Toledo Rd Southgate MI 48195-2506",
          "lat": 42.214,
          "lng": -83.194
        },
        {
          "id": "cpc-66259",
          "name": "Corewell Health Pediatrics",
          "area": "Canton",
          "type": "Primary Care",
          "sameDaySlots": 0,
          "nextDaySlots": 0,
          "nextAvailable": "Fri 4/17 \u2014 15 slots (first: 8:20 AM)",
          "nextAvailableDate": "Fri 4/17",
          "source": "MyChart",
          "lastChecked": "2026-04-14T11:59:53.361873",
          "address": "7330 N Canton Center Rd Ste 216 Canton MI 48187-1538",
          "lat": 42.26,
          "lng": -83.38
        },
        {
          "id": "cpc-55277",
          "name": "Corewell Health Family Medicine",
          "area": "Warren St Dearborn Heights",
          "type": "Primary Care",
          "sameDaySlots": 0,
          "nextDaySlots": 0,
          "nextAvailable": "Fri 4/17 \u2014 35 slots (first: 8:30 AM)",
          "nextAvailableDate": "Fri 4/17",
          "source": "MyChart",
          "lastChecked": "2026-04-14T11:59:53.361935",
          "address": "27031 W Warren St Dearborn Heights MI 48127-1901",
          "lat": 42.337,
          "lng": -83.273
        },
        {
          "id": "cpc-6282",
          "name": "Corewell Health Family Medicine",
          "area": "Canton",
          "type": "Primary Care",
          "sameDaySlots": 0,
          "nextDaySlots": 0,
          "nextAvailable": "Fri 4/17 \u2014 20 slots (first: 10:30 AM)",
          "nextAvailableDate": "Fri 4/17",
          "source": "MyChart",
          "lastChecked": "2026-04-14T11:59:53.361983",
          "address": "2050 N Haggerty Rd Ste 220 Canton MI 48187-3796",
          "lat": 42.26,
          "lng": -83.38
        },
        {
          "id": "cpc-79751",
          "name": "Corewell Health Family Medicine - Garden City",
          "area": "Ford Rd Garden City",
          "type": "Primary Care",
          "sameDaySlots": 0,
          "nextDaySlots": 0,
          "nextAvailable": "Fri 4/17 \u2014 18 slots (first: 9:00 AM)",
          "nextAvailableDate": "Fri 4/17",
          "source": "MyChart",
          "lastChecked": "2026-04-14T11:59:53.362037",
          "address": "29150 Ford Rd Garden City MI 48135-2848",
          "lat": 42.326,
          "lng": -83.331
        },
        {
          "id": "cpc-1064",
          "name": "Corewell Health Family Medicine",
          "area": "Dearborn",
          "type": "Primary Care",
          "sameDaySlots": 0,
          "nextDaySlots": 0,
          "nextAvailable": "Fri 4/17 \u2014 14 slots (first: 8:00 AM)",
          "nextAvailableDate": "Fri 4/17",
          "source": "MyChart",
          "lastChecked": "2026-04-14T11:59:53.362119",
          "address": "4700 Schaefer Rd Ste 150 Dearborn MI 48126-3655",
          "lat": 42.33,
          "lng": -83.18
        },
        {
          "id": "cpc-36648",
          "name": "Corewell Health Internal Medicine",
          "area": "Westland",
          "type": "Primary Care",
          "sameDaySlots": 0,
          "nextDaySlots": 0,
          "nextAvailable": "Fri 4/17 \u2014 17 slots (first: 3:30 PM)",
          "nextAvailableDate": "Fri 4/17",
          "source": "MyChart",
          "lastChecked": "2026-04-14T11:59:53.362287",
          "address": "35330 Nankin Blvd Ste 701 Westland MI 48185-7223",
          "lat": 42.324,
          "lng": -83.4
        },
        {
          "id": "cpc-8646",
          "name": "Corewell Health Family Medicine - Parkside",
          "area": "Oxford",
          "type": "Primary Care",
          "sameDaySlots": 0,
          "nextDaySlots": 0,
          "nextAvailable": "Fri 4/17 \u2014 2 slots (first: 8:00 AM)",
          "nextAvailableDate": "Fri 4/17",
          "source": "MyChart",
          "lastChecked": "2026-04-14T11:59:53.362378",
          "address": "25 S Washington St Ste A Oxford MI 48371-4978",
          "lat": 42.82,
          "lng": -83.27
        },
        {
          "id": "cpc-42707",
          "name": "Corewell Health Primary Care",
          "area": "Grosse Pointe",
          "type": "Primary Care",
          "sameDaySlots": 0,
          "nextDaySlots": 0,
          "nextAvailable": "Fri 4/17 \u2014 36 slots (first: 8:15 AM)",
          "nextAvailableDate": "Fri 4/17",
          "source": "MyChart",
          "lastChecked": "2026-04-14T11:59:53.362459",
          "address": "17000 Kercheval Ave Ste 205 Grosse Pointe MI 48230-1570",
          "lat": 42.387,
          "lng": -82.906
        },
        {
          "id": "cpc-93651",
          "name": "Corewell Health Internal Medicine",
          "area": "Farmington Rd Livonia",
          "type": "Primary Care",
          "sameDaySlots": 0,
          "nextDaySlots": 0,
          "nextAvailable": "Fri 4/17 \u2014 16 slots (first: 11:00 AM)",
          "nextAvailableDate": "Fri 4/17",
          "source": "MyChart",
          "lastChecked": "2026-04-14T11:59:53.362523",
          "address": "20317 Farmington Rd Livonia MI 48152-1411",
          "lat": 42.465,
          "lng": -83.377
        },
        {
          "id": "cpc-53688",
          "name": "Corewell Health Internal Medicine",
          "area": "Warren St Dearborn Heights",
          "type": "Primary Care",
          "sameDaySlots": 0,
          "nextDaySlots": 0,
          "nextAvailable": "Fri 4/17 \u2014 23 slots (first: 8:00 AM)",
          "nextAvailableDate": "Fri 4/17",
          "source": "MyChart",
          "lastChecked": "2026-04-14T11:59:53.362582",
          "address": "27015 W Warren St Dearborn Heights MI 48127-1901",
          "lat": 42.337,
          "lng": -83.273
        },
        {
          "id": "cpc-66106",
          "name": "Corewell Health Internal Medicine",
          "area": "Hubbard Dr Dearborn",
          "type": "Primary Care",
          "sameDaySlots": 0,
          "nextDaySlots": 0,
          "nextAvailable": "Fri 4/17 \u2014 16 slots (first: 9:30 AM)",
          "nextAvailableDate": "Fri 4/17",
          "source": "MyChart",
          "lastChecked": "2026-04-14T11:59:53.362641",
          "address": "17000 Hubbard Dr Dearborn MI 48126-4258",
          "lat": 42.322,
          "lng": -83.176
        },
        {
          "id": "cpc-22362",
          "name": "Corewell Health Family Medicine",
          "area": "Farmington Hills",
          "type": "Primary Care",
          "sameDaySlots": 0,
          "nextDaySlots": 0,
          "nextAvailable": "Fri 4/17 \u2014 6 slots (first: 9:00 AM)",
          "nextAvailableDate": "Fri 4/17",
          "source": "MyChart",
          "lastChecked": "2026-04-14T11:59:53.362695",
          "address": "29645 W 14 Mile Rd Ste 110 Farmington Hills MI 48334-1666",
          "lat": 42.498,
          "lng": -83.377
        },
        {
          "id": "cpc-60759",
          "name": "Corewell Health Family Medicine - Newport",
          "area": "Newport Rd Newport",
          "type": "Primary Care",
          "sameDaySlots": 0,
          "nextDaySlots": 0,
          "nextAvailable": "Fri 4/17 \u2014 15 slots (first: 7:00 AM)",
          "nextAvailableDate": "Fri 4/17",
          "source": "MyChart",
          "lastChecked": "2026-04-14T11:59:53.362755",
          "address": "3132 Newport Rd Newport MI 48166-6100",
          "lat": null,
          "lng": null
        },
        {
          "id": "cpc-39556",
          "name": "Corewell Health Family Medicine",
          "area": "Mile Rd Novi",
          "type": "Primary Care",
          "sameDaySlots": 0,
          "nextDaySlots": 0,
          "nextAvailable": "Fri 4/17 \u2014 11 slots (first: 8:00 AM)",
          "nextAvailableDate": "Fri 4/17",
          "source": "MyChart",
          "lastChecked": "2026-04-14T11:59:53.362812",
          "address": "44130 W 12 Mile Rd Novi MI 48377-2614",
          "lat": 42.48,
          "lng": -83.476
        },
        {
          "id": "cpc-97876",
          "name": "Corewell Health Family Medicine - Belleville",
          "area": "St Belleville",
          "type": "Primary Care",
          "sameDaySlots": 0,
          "nextDaySlots": 0,
          "nextAvailable": "Fri 4/17 \u2014 11 slots (first: 8:00 AM)",
          "nextAvailableDate": "Fri 4/17",
          "source": "MyChart",
          "lastChecked": "2026-04-14T11:59:53.362858",
          "address": "201 3rd St Belleville MI 48111-2605",
          "lat": 42.15,
          "lng": -83.36
        },
        {
          "id": "cpc-96233",
          "name": "Corewell Health Internal Medicine",
          "area": "Biddle Ave Wyandotte",
          "type": "Primary Care",
          "sameDaySlots": 0,
          "nextDaySlots": 0,
          "nextAvailable": "Fri 4/17 \u2014 12 slots (first: 9:30 AM)",
          "nextAvailableDate": "Fri 4/17",
          "source": "MyChart",
          "lastChecked": "2026-04-14T11:59:53.362902",
          "address": "1700 Biddle Ave Wyandotte MI 48192-7205",
          "lat": 42.21,
          "lng": -83.18
        },
        {
          "id": "cpc-42195",
          "name": "Corewell Health Internal Medicine",
          "area": "Warren St Dearborn Heights",
          "type": "Primary Care",
          "sameDaySlots": 0,
          "nextDaySlots": 0,
          "nextAvailable": "Fri 4/17 \u2014 23 slots (first: 10:15 AM)",
          "nextAvailableDate": "Fri 4/17",
          "source": "MyChart",
          "lastChecked": "2026-04-14T11:59:53.362956",
          "address": "27015 W Warren St Dearborn Heights MI 48127-1901",
          "lat": 42.337,
          "lng": -83.273
        },
        {
          "id": "cpc-21257",
          "name": "Corewell Health Internal Medicine",
          "area": "Canton",
          "type": "Primary Care",
          "sameDaySlots": 0,
          "nextDaySlots": 0,
          "nextAvailable": "Fri 4/17 \u2014 7 slots (first: 11:00 AM)",
          "nextAvailableDate": "Fri 4/17",
          "source": "MyChart",
          "lastChecked": "2026-04-14T11:59:53.363000",
          "address": "2050 N Haggerty Rd Ste 100 Canton MI 48187-3796",
          "lat": 42.26,
          "lng": -83.38
        },
        {
          "id": "cpc-92165",
          "name": "Corewell Health Family Medicine - Livonia/Northville with Kerry Stone.",
          "area": "Livonia",
          "type": "Primary Care",
          "sameDaySlots": 0,
          "nextDaySlots": 0,
          "nextAvailable": "Fri 4/17 \u2014 14 slots (first: 8:30 AM)",
          "nextAvailableDate": "Fri 4/17",
          "source": "MyChart",
          "lastChecked": "2026-04-14T11:59:53.363059",
          "address": "39000 7 Mile Rd Ste 4300 Livonia MI 48152-1006",
          "lat": 42.368,
          "lng": -83.353
        },
        {
          "id": "cpc-48642",
          "name": "Corewell Health Family Medicine",
          "area": "Plaza Dr Taylor",
          "type": "Primary Care",
          "sameDaySlots": 0,
          "nextDaySlots": 0,
          "nextAvailable": "Fri 4/17 \u2014 12 slots (first: 10:30 AM)",
          "nextAvailableDate": "Fri 4/17",
          "source": "MyChart",
          "lastChecked": "2026-04-14T11:59:53.363116",
          "address": "15100 S Plaza Dr Taylor MI 48180-5203",
          "lat": 42.241,
          "lng": -83.269
        },
        {
          "id": "cpc-48914",
          "name": "Corewell Health Internal Medicine",
          "area": "Biddle Ave Wyandotte",
          "type": "Primary Care",
          "sameDaySlots": 0,
          "nextDaySlots": 0,
          "nextAvailable": "Sat 4/18 \u2014 1 slots (first: 12:30 PM)",
          "nextAvailableDate": "Sat 4/18",
          "source": "MyChart",
          "lastChecked": "2026-04-14T11:59:53.363158",
          "address": "1700 Biddle Ave Wyandotte MI 48192-7205",
          "lat": 42.21,
          "lng": -83.18
        },
        {
          "id": "cpc-41851",
          "name": "Corewell Health Pediatrics",
          "area": "Orchard Lake Rd Farmington",
          "type": "Primary Care",
          "sameDaySlots": 0,
          "nextDaySlots": 0,
          "nextAvailable": "Mon 4/20 \u2014 10 slots (first: 9:00 AM)",
          "nextAvailableDate": "Mon 4/20",
          "source": "MyChart",
          "lastChecked": "2026-04-14T11:59:53.363211",
          "address": "23133 Orchard Lake Rd Farmington MI 48336-3268",
          "lat": 42.465,
          "lng": -83.377
        },
        {
          "id": "cpc-94014",
          "name": "Corewell Health Family Medicine",
          "area": "Telegraph Rd Taylor",
          "type": "Primary Care",
          "sameDaySlots": 0,
          "nextDaySlots": 0,
          "nextAvailable": "Mon 4/20 \u2014 1 slots (first: 10:30 AM)",
          "nextAvailableDate": "Mon 4/20",
          "source": "MyChart",
          "lastChecked": "2026-04-14T11:59:53.363251",
          "address": "9340 Telegraph Rd Taylor MI 48180-3362",
          "lat": 42.24,
          "lng": -83.21
        },
        {
          "id": "cpc-90418",
          "name": "Corewell Health Family Medicine",
          "area": "Warren",
          "type": "Primary Care",
          "sameDaySlots": 0,
          "nextDaySlots": 0,
          "nextAvailable": "Mon 4/20 \u2014 13 slots (first: 1:30 PM)",
          "nextAvailableDate": "Mon 4/20",
          "source": "MyChart",
          "lastChecked": "2026-04-14T11:59:53.363294",
          "address": "8545 Common Rd Ste 280 Warren MI 48093-6775",
          "lat": 42.53,
          "lng": -83.05
        },
        {
          "id": "cpc-83255",
          "name": "Corewell Health Family Medicine",
          "area": "Grand River Ave Farmington",
          "type": "Primary Care",
          "sameDaySlots": 0,
          "nextDaySlots": 0,
          "nextAvailable": "Mon 4/20 \u2014 8 slots (first: 8:30 AM)",
          "nextAvailableDate": "Mon 4/20",
          "source": "MyChart",
          "lastChecked": "2026-04-14T11:59:53.363346",
          "address": "32754 Grand River Ave Farmington MI 48336-3133",
          "lat": 42.465,
          "lng": -83.377
        },
        {
          "id": "cpc-64228",
          "name": "Corewell Health Primary Care",
          "area": "Kercheval Ave Grosse Pointe Park",
          "type": "Primary Care",
          "sameDaySlots": 0,
          "nextDaySlots": 0,
          "nextAvailable": "Mon 4/20 \u2014 22 slots (first: 1:30 PM)",
          "nextAvailableDate": "Mon 4/20",
          "source": "MyChart",
          "lastChecked": "2026-04-14T11:59:53.363399",
          "address": "15200 Kercheval Ave Grosse Pointe Park MI 48230-1356",
          "lat": 42.387,
          "lng": -82.906
        },
        {
          "id": "cpc-66618",
          "name": "Corewell Health Internal Medicine",
          "area": "Canton",
          "type": "Primary Care",
          "sameDaySlots": 0,
          "nextDaySlots": 0,
          "nextAvailable": "Mon 4/20 \u2014 6 slots (first: 8:30 AM)",
          "nextAvailableDate": "Mon 4/20",
          "source": "MyChart",
          "lastChecked": "2026-04-14T11:59:53.363445",
          "address": "7330 N Canton Center Rd Ste 209 Canton MI 48187-1538",
          "lat": 42.26,
          "lng": -83.38
        },
        {
          "id": "cpc-14679",
          "name": "Corewell Health Pediatrics",
          "area": "Orchard Lake Rd Farmington",
          "type": "Primary Care",
          "sameDaySlots": 0,
          "nextDaySlots": 0,
          "nextAvailable": "Thu 4/23 \u2014 5 slots (first: 11:30 AM)",
          "nextAvailableDate": "Thu 4/23",
          "source": "MyChart",
          "lastChecked": "2026-04-14T11:59:53.363499",
          "address": "23133 Orchard Lake Rd Farmington MI 48336-3268",
          "lat": 42.465,
          "lng": -83.377
        }
      ]
    },
    "corewell_uc": {
      "name": "Corewell Health Urgent Care",
      "locations": [
        {
          "id": "cuc-1",
          "name": "Corewell UC \u2014 Rochester Hills",
          "area": "Rochester Hills",
          "type": "Urgent Care",
          "sameDaySlots": 10,
          "nextDaySlots": 0,
          "nextAvailable": "Today \u2014 10 slots (next: 12:02)",
          "nextAvailableDate": "Today",
          "source": "corewellhealthurgentcarese.com",
          "lastChecked": "2026-04-14T11:56:20.902021",
          "address": "3200 Walton Boulevard Rochester Hills, MI",
          "lat": 42.659,
          "lng": -83.15
        },
        {
          "id": "cuc-2",
          "name": "Corewell UC \u2014 Lake Orion",
          "area": "Lake Orion",
          "type": "Urgent Care",
          "sameDaySlots": 10,
          "nextDaySlots": 0,
          "nextAvailable": "Today \u2014 10 slots (next: 12:00)",
          "nextAvailableDate": "Today",
          "source": "corewellhealthurgentcarese.com",
          "lastChecked": "2026-04-14T11:56:20.902085",
          "address": "845 S. Lapeer Rd. Orion Charter Township, MI",
          "lat": 42.782,
          "lng": -83.243
        },
        {
          "id": "cuc-3",
          "name": "Corewell UC \u2014 Troy Big Beaver",
          "area": "Troy Big Beaver",
          "type": "Urgent Care",
          "sameDaySlots": 10,
          "nextDaySlots": 0,
          "nextAvailable": "Today \u2014 10 slots (next: 12:00)",
          "nextAvailableDate": "Today",
          "source": "corewellhealthurgentcarese.com",
          "lastChecked": "2026-04-14T11:56:20.902129",
          "address": "2078 E. Big Beaver Road Troy, MI",
          "lat": 42.606,
          "lng": -83.15
        },
        {
          "id": "cuc-4",
          "name": "Corewell UC \u2014 Macomb",
          "area": "Macomb",
          "type": "Urgent Care",
          "sameDaySlots": 10,
          "nextDaySlots": 0,
          "nextAvailable": "Today \u2014 10 slots (next: 12:00)",
          "nextAvailableDate": "Today",
          "source": "corewellhealthurgentcarese.com",
          "lastChecked": "2026-04-14T11:56:20.902167",
          "address": "15959 Hall Road Macomb, MI",
          "lat": 42.672,
          "lng": -82.912
        },
        {
          "id": "cuc-5",
          "name": "Corewell UC \u2014 Royal Oak Woodward Corners",
          "area": "Royal Oak Woodward Corners",
          "type": "Urgent Care",
          "sameDaySlots": 10,
          "nextDaySlots": 0,
          "nextAvailable": "Today \u2014 10 slots (next: 11:56)",
          "nextAvailableDate": "Today",
          "source": "corewellhealthurgentcarese.com",
          "lastChecked": "2026-04-14T11:56:20.902201",
          "address": "30955 Woodward Avenue Royal Oak, MI",
          "lat": 42.489,
          "lng": -83.144
        },
        {
          "id": "cuc-6",
          "name": "Corewell UC \u2014 Chesterfield",
          "area": "Chesterfield",
          "type": "Urgent Care",
          "sameDaySlots": 10,
          "nextDaySlots": 0,
          "nextAvailable": "Today \u2014 10 slots (next: 11:56)",
          "nextAvailableDate": "Today",
          "source": "corewellhealthurgentcarese.com",
          "lastChecked": "2026-04-14T11:56:20.902234",
          "address": "50964 Gratiot Ave Chesterfield, MI",
          "lat": 42.673,
          "lng": -82.838
        },
        {
          "id": "cuc-7",
          "name": "Corewell UC \u2014 Shelby Township",
          "area": "Shelby Township",
          "type": "Urgent Care",
          "sameDaySlots": 10,
          "nextDaySlots": 0,
          "nextAvailable": "Today \u2014 10 slots (next: 11:57)",
          "nextAvailableDate": "Today",
          "source": "corewellhealthurgentcarese.com",
          "lastChecked": "2026-04-14T11:56:20.902262",
          "address": "56293 Van Dyke Ave Shelby Township, MI",
          "lat": 42.671,
          "lng": -83.032
        },
        {
          "id": "cuc-8",
          "name": "Corewell UC \u2014 Bloomfield Township",
          "area": "Bloomfield Township",
          "type": "Urgent Care",
          "sameDaySlots": 10,
          "nextDaySlots": 0,
          "nextAvailable": "Today \u2014 10 slots (next: 11:56)",
          "nextAvailableDate": "Today",
          "source": "corewellhealthurgentcarese.com",
          "lastChecked": "2026-04-14T11:56:20.902296",
          "address": "6543 Telegraph Road Bloomfield Township, MI",
          "lat": 42.583,
          "lng": -83.245
        },
        {
          "id": "cuc-9",
          "name": "Corewell UC \u2014 Novi",
          "area": "Novi",
          "type": "Urgent Care",
          "sameDaySlots": 10,
          "nextDaySlots": 0,
          "nextAvailable": "Today \u2014 10 slots (next: 12:00)",
          "nextAvailableDate": "Today",
          "source": "corewellhealthurgentcarese.com",
          "lastChecked": "2026-04-14T11:56:20.902328",
          "address": "43535 Grand River Ave Novi, MI",
          "lat": 42.48,
          "lng": -83.476
        },
        {
          "id": "cuc-0",
          "name": "Corewell UC \u2014 Southgate",
          "area": "Southgate",
          "type": "Urgent Care",
          "sameDaySlots": 10,
          "nextDaySlots": 0,
          "nextAvailable": "Today \u2014 10 slots (next: 12:04)",
          "nextAvailableDate": "Today",
          "source": "corewellhealthurgentcarese.com",
          "lastChecked": "2026-04-14T11:56:20.902360",
          "address": "16525 Fort Street Southgate, MI",
          "lat": 42.214,
          "lng": -83.194
        },
        {
          "id": "cuc-1",
          "name": "Corewell UC \u2014 Warren West",
          "area": "Warren West",
          "type": "Urgent Care",
          "sameDaySlots": 10,
          "nextDaySlots": 0,
          "nextAvailable": "Today \u2014 10 slots (next: 12:00)",
          "nextAvailableDate": "Today",
          "source": "corewellhealthurgentcarese.com",
          "lastChecked": "2026-04-14T11:56:20.902392",
          "address": "28284 Dequindre Road Warren, MI",
          "lat": 42.49,
          "lng": -83.027
        },
        {
          "id": "cuc-2",
          "name": "Corewell UC \u2014 Taylor",
          "area": "Taylor",
          "type": "Urgent Care",
          "sameDaySlots": 10,
          "nextDaySlots": 0,
          "nextAvailable": "Today \u2014 10 slots (next: 11:56)",
          "nextAvailableDate": "Today",
          "source": "corewellhealthurgentcarese.com",
          "lastChecked": "2026-04-14T11:56:20.902424",
          "address": "9870 Telegraph Road Taylor, MI",
          "lat": 42.241,
          "lng": -83.269
        },
        {
          "id": "cuc-3",
          "name": "Corewell UC \u2014 Allen Park",
          "area": "Allen Park",
          "type": "Urgent Care",
          "sameDaySlots": 10,
          "nextDaySlots": 0,
          "nextAvailable": "Today \u2014 10 slots (next: 12:04)",
          "nextAvailableDate": "Today",
          "source": "corewellhealthurgentcarese.com",
          "lastChecked": "2026-04-14T11:56:20.902453",
          "address": "15606 Southfield Road Allen Park, MI",
          "lat": 42.473,
          "lng": -83.222
        },
        {
          "id": "cuc-4",
          "name": "Corewell UC \u2014 Bloomfield Hills",
          "area": "Bloomfield Hills",
          "type": "Urgent Care",
          "sameDaySlots": 10,
          "nextDaySlots": 0,
          "nextAvailable": "Today \u2014 10 slots (next: 12:04)",
          "nextAvailableDate": "Today",
          "source": "corewellhealthurgentcarese.com",
          "lastChecked": "2026-04-14T11:56:20.902483",
          "address": "42757 Woodward Ave Bloomfield Hills, MI",
          "lat": 42.583,
          "lng": -83.245
        },
        {
          "id": "cuc-5",
          "name": "Corewell UC \u2014 Warren East",
          "area": "Warren East",
          "type": "Urgent Care",
          "sameDaySlots": 10,
          "nextDaySlots": 0,
          "nextAvailable": "Today \u2014 10 slots (next: 12:00)",
          "nextAvailableDate": "Today",
          "source": "corewellhealthurgentcarese.com",
          "lastChecked": "2026-04-14T11:56:20.902527",
          "address": "28550 Schoenherr Road Warren, MI",
          "lat": 42.49,
          "lng": -83.027
        },
        {
          "id": "cuc-6",
          "name": "Corewell UC \u2014 Grosse Pointe Farms",
          "area": "Grosse Pointe Farms",
          "type": "Urgent Care",
          "sameDaySlots": 10,
          "nextDaySlots": 0,
          "nextAvailable": "Today \u2014 10 slots (next: 11:56)",
          "nextAvailableDate": "Today",
          "source": "corewellhealthurgentcarese.com",
          "lastChecked": "2026-04-14T11:56:20.902557",
          "address": "18700 Mack Avenue Grosse Pointe Farms, MI",
          "lat": 42.387,
          "lng": -82.906
        },
        {
          "id": "cuc-7",
          "name": "Corewell UC \u2014 Dearborn",
          "area": "Dearborn",
          "type": "Urgent Care",
          "sameDaySlots": 10,
          "nextDaySlots": 0,
          "nextAvailable": "Today \u2014 10 slots (next: 11:56)",
          "nextAvailableDate": "Today",
          "source": "corewellhealthurgentcarese.com",
          "lastChecked": "2026-04-14T11:56:20.902591",
          "address": "23100 Michigan Ave Dearborn, MI",
          "lat": 42.322,
          "lng": -83.176
        },
        {
          "id": "cuc-8",
          "name": "Corewell UC \u2014 Haggerty Square",
          "area": "Haggerty Square",
          "type": "Urgent Care",
          "sameDaySlots": 10,
          "nextDaySlots": 0,
          "nextAvailable": "Today \u2014 10 slots (next: 11:56)",
          "nextAvailableDate": "Today",
          "source": "corewellhealthurgentcarese.com",
          "lastChecked": "2026-04-14T11:56:20.902623",
          "address": "19760 Haggerty Road Livonia, MI",
          "lat": 42.368,
          "lng": -83.353
        },
        {
          "id": "cuc-9",
          "name": "Corewell UC \u2014 Downtown Royal Oak",
          "area": "Downtown Royal Oak",
          "type": "Urgent Care",
          "sameDaySlots": 10,
          "nextDaySlots": 0,
          "nextAvailable": "Today \u2014 10 slots (next: 12:00)",
          "nextAvailableDate": "Today",
          "source": "corewellhealthurgentcarese.com",
          "lastChecked": "2026-04-14T11:56:20.902655",
          "address": "309 E 11 Mile Road Royal Oak, MI",
          "lat": 42.489,
          "lng": -83.144
        },
        {
          "id": "cuc-0",
          "name": "Corewell UC \u2014 Farmington Hills North",
          "area": "Farmington Hills North",
          "type": "Urgent Care",
          "sameDaySlots": 10,
          "nextDaySlots": 0,
          "nextAvailable": "Today \u2014 10 slots (next: 12:00)",
          "nextAvailableDate": "Today",
          "source": "corewellhealthurgentcarese.com",
          "lastChecked": "2026-04-14T11:56:20.902687",
          "address": "29263 Orchard Lake Road Farmington Hills, MI",
          "lat": 42.498,
          "lng": -83.377
        },
        {
          "id": "cuc-1",
          "name": "Corewell UC \u2014 Wayne",
          "area": "Wayne",
          "type": "Urgent Care",
          "sameDaySlots": 10,
          "nextDaySlots": 0,
          "nextAvailable": "Today \u2014 10 slots (next: 11:56)",
          "nextAvailableDate": "Today",
          "source": "corewellhealthurgentcarese.com",
          "lastChecked": "2026-04-14T11:56:20.902718",
          "address": "34435 Michigan Avenue Wayne, MI",
          "lat": 42.282,
          "lng": -83.386
        },
        {
          "id": "cuc-2",
          "name": "Corewell UC \u2014 Farmington Hills South",
          "area": "Farmington Hills South",
          "type": "Urgent Care",
          "sameDaySlots": 10,
          "nextDaySlots": 0,
          "nextAvailable": "Today \u2014 10 slots (next: 12:09)",
          "nextAvailableDate": "Today",
          "source": "corewellhealthurgentcarese.com",
          "lastChecked": "2026-04-14T11:56:20.902749",
          "address": "27810 Grand River Avenue Farmington Hills, MI",
          "lat": 42.498,
          "lng": -83.377
        },
        {
          "id": "cuc-3",
          "name": "Corewell UC \u2014 Woodhaven",
          "area": "Woodhaven",
          "type": "Urgent Care",
          "sameDaySlots": 10,
          "nextDaySlots": 0,
          "nextAvailable": "Today \u2014 10 slots (next: 11:57)",
          "nextAvailableDate": "Today",
          "source": "corewellhealthurgentcarese.com",
          "lastChecked": "2026-04-14T11:56:20.902779",
          "address": "18930 West Road Woodhaven, MI",
          "lat": 42.139,
          "lng": -83.242
        },
        {
          "id": "cuc-4",
          "name": "Corewell UC \u2014 Canton Michigan",
          "area": "Canton Michigan",
          "type": "Urgent Care",
          "sameDaySlots": 10,
          "nextDaySlots": 0,
          "nextAvailable": "Today \u2014 10 slots (next: 11:56)",
          "nextAvailableDate": "Today",
          "source": "corewellhealthurgentcarese.com",
          "lastChecked": "2026-04-14T11:56:20.902813",
          "address": "6549 N. Canton Center Road Canton, MI",
          "lat": 42.309,
          "lng": -83.482
        },
        {
          "id": "cuc-5",
          "name": "Corewell UC \u2014 Troy Square Lake",
          "area": "Troy Square Lake",
          "type": "Urgent Care",
          "sameDaySlots": 10,
          "nextDaySlots": 0,
          "nextAvailable": "Today \u2014 10 slots (next: 11:57)",
          "nextAvailableDate": "Today",
          "source": "corewellhealthurgentcarese.com",
          "lastChecked": "2026-04-14T11:56:20.902854",
          "address": "43037 Dequindre Road Troy, MI",
          "lat": 42.606,
          "lng": -83.15
        },
        {
          "id": "cuc-6",
          "name": "Corewell UC \u2014 West Bloomfield",
          "area": "West Bloomfield",
          "type": "Urgent Care",
          "sameDaySlots": 10,
          "nextDaySlots": 0,
          "nextAvailable": "Today \u2014 10 slots (next: 12:00)",
          "nextAvailableDate": "Today",
          "source": "corewellhealthurgentcarese.com",
          "lastChecked": "2026-04-14T11:56:20.902885",
          "address": "6470 Orchard Lake Road West Bloomfield, MI",
          "lat": 42.565,
          "lng": -83.382
        },
        {
          "id": "cuc-7",
          "name": "Corewell UC \u2014 St Clair Shores",
          "area": "St Clair Shores",
          "type": "Urgent Care",
          "sameDaySlots": 10,
          "nextDaySlots": 0,
          "nextAvailable": "Today \u2014 10 slots (next: 11:57)",
          "nextAvailableDate": "Today",
          "source": "corewellhealthurgentcarese.com",
          "lastChecked": "2026-04-14T11:56:20.902915",
          "address": "25631 Little Mack Avenue St Clair Shores, MI",
          "lat": 42.497,
          "lng": -82.891
        },
        {
          "id": "cuc-8",
          "name": "Corewell UC \u2014 Garden City",
          "area": "Garden City",
          "type": "Urgent Care",
          "sameDaySlots": 10,
          "nextDaySlots": 0,
          "nextAvailable": "Today \u2014 10 slots (next: 11:56)",
          "nextAvailableDate": "Today",
          "source": "corewellhealthurgentcarese.com",
          "lastChecked": "2026-04-14T11:56:20.902953",
          "address": "6200 Middlebelt Road Garden City, MI",
          "lat": 42.326,
          "lng": -83.331
        }
      ]
    },
    "henryford_pc": {
      "name": "Henry Ford Primary Care",
      "locations": [
        {
          "id": "hfpc-80036",
          "name": "Henry Ford Medical Center - Beck Rd with Jamie Fineran, CNP.",
          "area": "Beck Rd Plymouth",
          "type": "Primary Care",
          "sameDaySlots": 3,
          "nextDaySlots": 0,
          "nextAvailable": "Fri 3/27 \u2014 3 slots (first: 1:00 PM)",
          "nextAvailableDate": "Fri 3/27",
          "source": "MyChart",
          "lastChecked": "2026-03-27T10:48:46.424827",
          "address": "14300 Beck Rd Plymouth MI 48170",
          "lat": 42.371,
          "lng": -83.47
        },
        {
          "id": "hfpc-11978",
          "name": "Henry Ford Medical Center - Farmington Rd with Stephanie Guilford, PA-C.",
          "area": "",
          "type": "Primary Care",
          "sameDaySlots": 2,
          "nextDaySlots": 0,
          "nextAvailable": "Fri 3/27 \u2014 2 slots (first: 11:20 AM)",
          "nextAvailableDate": "Fri 3/27",
          "source": "MyChart",
          "lastChecked": "2026-03-27T10:48:46.425993",
          "address": "",
          "lat": null,
          "lng": null
        },
        {
          "id": "hfpc-11392",
          "name": "Henry Ford Medical Center - Ford Rd with Tahniyat Gul, DO.",
          "area": "Auto Club Dr Dearborn",
          "type": "Primary Care",
          "sameDaySlots": 1,
          "nextDaySlots": 0,
          "nextAvailable": "Fri 3/27 \u2014 1 slots (first: 1:40 PM)",
          "nextAvailableDate": "Fri 3/27",
          "source": "MyChart",
          "lastChecked": "2026-03-27T10:48:46.427583",
          "address": "5500 Auto Club Dr Dearborn MI 48126",
          "lat": 42.33,
          "lng": -83.18
        },
        {
          "id": "hfpc-2690",
          "name": "Henry Ford Medical Center - Ford Rd with Rima Hall, CNP.",
          "area": "Auto Club Dr Dearborn",
          "type": "Primary Care",
          "sameDaySlots": 6,
          "nextDaySlots": 0,
          "nextAvailable": "Fri 3/27 \u2014 6 slots (first: 1:40 PM)",
          "nextAvailableDate": "Fri 3/27",
          "source": "MyChart",
          "lastChecked": "2026-03-27T10:48:46.428221",
          "address": "5500 Auto Club Dr Dearborn MI 48126",
          "lat": 42.33,
          "lng": -83.18
        },
        {
          "id": "hfpc-29061",
          "name": "Henry Ford Medical Center - Royal Oak with Andy Li, CNP.",
          "area": "Floor Royal Oak",
          "type": "Primary Care",
          "sameDaySlots": 4,
          "nextDaySlots": 0,
          "nextAvailable": "Fri 3/27 \u2014 4 slots (first: 1:00 PM)",
          "nextAvailableDate": "Fri 3/27",
          "source": "MyChart",
          "lastChecked": "2026-03-27T10:48:46.429151",
          "address": "110 E 2nd St 3rd Floor Royal Oak MI 48067",
          "lat": 42.49,
          "lng": -83.14
        },
        {
          "id": "hfpc-84614",
          "name": "Henry Ford Medical Center - Livonia with Li Li, MD.",
          "area": "Schoolcraft Rd Livonia",
          "type": "Primary Care",
          "sameDaySlots": 1,
          "nextDaySlots": 0,
          "nextAvailable": "Fri 3/27 \u2014 1 slots (first: 11:00 AM)",
          "nextAvailableDate": "Fri 3/27",
          "source": "MyChart",
          "lastChecked": "2026-03-27T10:48:46.429857",
          "address": "29200 Schoolcraft Rd Livonia MI 48150",
          "lat": 42.368,
          "lng": -83.353
        },
        {
          "id": "hfpc-25383",
          "name": "Henry Ford Medical Center - Leslie with Stanley Sczecienski, DO.",
          "area": "Sherman St Leslie",
          "type": "Primary Care",
          "sameDaySlots": 1,
          "nextDaySlots": 0,
          "nextAvailable": "Fri 3/27 \u2014 1 slots (first: 1:40 PM)",
          "nextAvailableDate": "Fri 3/27",
          "source": "MyChart",
          "lastChecked": "2026-03-27T10:48:46.430532",
          "address": "130 N Sherman St Leslie MI 49251-9409",
          "lat": null,
          "lng": null
        },
        {
          "id": "hfpc-59184",
          "name": "Henry Ford Medical Center - Templin with Vijay Sharma, MD.",
          "area": "Biddle Ave Wyandotte",
          "type": "Primary Care",
          "sameDaySlots": 1,
          "nextDaySlots": 0,
          "nextAvailable": "Fri 3/27 \u2014 1 slots (first: 2:40 PM)",
          "nextAvailableDate": "Fri 3/27",
          "source": "MyChart",
          "lastChecked": "2026-03-27T10:48:46.431145",
          "address": "2070 Biddle Ave Wyandotte MI 48192-4031",
          "lat": 42.21,
          "lng": -83.18
        },
        {
          "id": "hfpc-98216",
          "name": "Henry Ford Medical Center - Livonia with Marguerite Sheffield, MD.",
          "area": "Schoolcraft Rd Livonia",
          "type": "Primary Care",
          "sameDaySlots": 2,
          "nextDaySlots": 0,
          "nextAvailable": "Fri 3/27 \u2014 2 slots (first: 3:00 PM)",
          "nextAvailableDate": "Fri 3/27",
          "source": "MyChart",
          "lastChecked": "2026-03-27T10:48:46.431878",
          "address": "29200 Schoolcraft Rd Livonia MI 48150",
          "lat": 42.368,
          "lng": -83.353
        },
        {
          "id": "hfpc-96113",
          "name": "Henry Ford Medical Center - Bloomfield Twp with Alison Yousif, FNP-BC.",
          "area": "Telegraph Rd Bloomfield Twp",
          "type": "Primary Care",
          "sameDaySlots": 11,
          "nextDaySlots": 0,
          "nextAvailable": "Fri 3/27 \u2014 11 slots (first: 2:00 PM)",
          "nextAvailableDate": "Fri 3/27",
          "source": "MyChart",
          "lastChecked": "2026-03-27T10:48:46.432736",
          "address": "1961 S Telegraph Rd Bloomfield Twp MI 48302",
          "lat": 42.61,
          "lng": -83.28
        },
        {
          "id": "hfpc-70353",
          "name": "Henry Ford Medical Center - Plymouth with Laila Abdallah, DO.",
          "area": "Ann Arbor Rd Plymouth",
          "type": "Primary Care",
          "sameDaySlots": 0,
          "nextDaySlots": 0,
          "nextAvailable": "Mon 3/30 \u2014 1 slots (first: 9:20 AM)",
          "nextAvailableDate": "Mon 3/30",
          "source": "MyChart",
          "lastChecked": "2026-03-27T10:48:46.433577",
          "address": "40777 Ann Arbor Rd Plymouth MI 48170",
          "lat": 42.281,
          "lng": -83.749
        },
        {
          "id": "hfpc-44092",
          "name": "Henry Ford Medical Center - Columbus with Caroline Bauer, AGPCNP.",
          "area": "Mile Rd Novi",
          "type": "Primary Care",
          "sameDaySlots": 0,
          "nextDaySlots": 0,
          "nextAvailable": "Mon 3/30 \u2014 22 slots (first: 10:00 AM)",
          "nextAvailableDate": "Mon 3/30",
          "source": "MyChart",
          "lastChecked": "2026-03-27T10:48:46.434308",
          "address": "39450 W 12 Mile Rd Novi MI 48377",
          "lat": 42.48,
          "lng": -83.476
        },
        {
          "id": "hfpc-44210",
          "name": "Henry Ford Family Medicine - Allen Park with Bradley Centala, PA.",
          "area": "Allen Rd Allen Park",
          "type": "Primary Care",
          "sameDaySlots": 0,
          "nextDaySlots": 0,
          "nextAvailable": "Mon 3/30 \u2014 9 slots (first: 11:20 AM)",
          "nextAvailableDate": "Mon 3/30",
          "source": "MyChart",
          "lastChecked": "2026-03-27T10:48:46.434941",
          "address": "7226 Allen Rd Allen Park MI 48101",
          "lat": 42.27,
          "lng": -83.24
        },
        {
          "id": "hfpc-97324",
          "name": "Henry Ford Medical Center - Woodhaven with Hunter Kuzmiak, CNP.",
          "area": "Allen Rd Woodhaven",
          "type": "Primary Care",
          "sameDaySlots": 0,
          "nextDaySlots": 0,
          "nextAvailable": "Mon 3/30 \u2014 11 slots (first: 1:00 PM)",
          "nextAvailableDate": "Mon 3/30",
          "source": "MyChart",
          "lastChecked": "2026-03-27T10:48:46.435580",
          "address": "22505 Allen Rd Woodhaven MI 48183",
          "lat": 42.139,
          "lng": -83.242
        },
        {
          "id": "hfpc-93313",
          "name": "Henry Ford Medical Center - Commerce with Brett Pelowski, DO.",
          "area": "Commerce Township",
          "type": "Primary Care",
          "sameDaySlots": 0,
          "nextDaySlots": 0,
          "nextAvailable": "Mon 3/30 \u2014 5 slots (first: 4:20 PM)",
          "nextAvailableDate": "Mon 3/30",
          "source": "MyChart",
          "lastChecked": "2026-03-27T10:48:46.435977",
          "address": "8391 Commerce Rd Ste 108 Commerce Township MI 48382",
          "lat": 42.56,
          "lng": -83.49
        },
        {
          "id": "hfpc-77451",
          "name": "Henry Ford Medical Center - Warren with Muhammad Shabbir, MD.",
          "area": "Warren",
          "type": "Primary Care",
          "sameDaySlots": 0,
          "nextDaySlots": 0,
          "nextAvailable": "Mon 3/30 \u2014 24 slots (first: 12:20 PM)",
          "nextAvailableDate": "Mon 3/30",
          "source": "MyChart",
          "lastChecked": "2026-03-27T10:48:46.436277",
          "address": "8600 Chicago Rd S Warren MI 48093",
          "lat": 42.53,
          "lng": -83.05
        },
        {
          "id": "hfpc-46172",
          "name": "Henry Ford Medical Center - E Jefferson with Rehana Siddiqui, MD.",
          "area": "Jefferson Ave Saint Clair Shores",
          "type": "Primary Care",
          "sameDaySlots": 0,
          "nextDaySlots": 0,
          "nextAvailable": "Mon 3/30 \u2014 1 slots (first: 11:00 AM)",
          "nextAvailableDate": "Mon 3/30",
          "source": "MyChart",
          "lastChecked": "2026-03-27T10:48:46.436643",
          "address": "24725 Jefferson Ave Saint Clair Shores MI 48080",
          "lat": 42.497,
          "lng": -82.891
        },
        {
          "id": "hfpc-32512",
          "name": "Henry Ford Medical Center - Brownstown with David White, FNP.",
          "area": "Brownstown",
          "type": "Primary Care",
          "sameDaySlots": 0,
          "nextDaySlots": 0,
          "nextAvailable": "Tue 3/31 \u2014 15 slots (first: 8:00 AM)",
          "nextAvailableDate": "Tue 3/31",
          "source": "MyChart",
          "lastChecked": "2026-03-27T10:48:46.437501",
          "address": "23050 West Rd Ste 260 Brownstown MI 48183",
          "lat": 42.156,
          "lng": -83.281
        },
        {
          "id": "hfpc-28393",
          "name": "Henry Ford Medical Center - Columbus with Diane Abel-Williams, PA.",
          "area": "Mile Rd Novi",
          "type": "Primary Care",
          "sameDaySlots": 0,
          "nextDaySlots": 0,
          "nextAvailable": "Tue 3/31 \u2014 14 slots (first: 1:00 PM)",
          "nextAvailableDate": "Tue 3/31",
          "source": "MyChart",
          "lastChecked": "2026-03-27T10:48:46.438097",
          "address": "39450 W 12 Mile Rd Novi MI 48377",
          "lat": 42.48,
          "lng": -83.476
        },
        {
          "id": "hfpc-1463",
          "name": "Henry Ford Medical Center - E Jefferson with Edgar Altares, MD.",
          "area": "Jefferson Ave Saint Clair Shores",
          "type": "Primary Care",
          "sameDaySlots": 0,
          "nextDaySlots": 0,
          "nextAvailable": "Tue 3/31 \u2014 1 slots (first: 8:40 AM)",
          "nextAvailableDate": "Tue 3/31",
          "source": "MyChart",
          "lastChecked": "2026-03-27T10:48:46.438616",
          "address": "24725 Jefferson Ave Saint Clair Shores MI 48080",
          "lat": 42.497,
          "lng": -82.891
        },
        {
          "id": "hfpc-89380",
          "name": "Henry Ford Medical Center - E Jefferson with Christopher Bracken, MD.",
          "area": "Jefferson Ave Saint Clair Shores",
          "type": "Primary Care",
          "sameDaySlots": 0,
          "nextDaySlots": 0,
          "nextAvailable": "Tue 3/31 \u2014 3 slots (first: 10:40 AM)",
          "nextAvailableDate": "Tue 3/31",
          "source": "MyChart",
          "lastChecked": "2026-03-27T10:48:46.439239",
          "address": "24725 Jefferson Ave Saint Clair Shores MI 48080",
          "lat": 42.497,
          "lng": -82.891
        },
        {
          "id": "hfpc-58435",
          "name": "Henry Ford Medical Center - Lakeside with Katie Hamelink, PA-C.",
          "area": "Hall Rd Sterling Hgts",
          "type": "Primary Care",
          "sameDaySlots": 0,
          "nextDaySlots": 0,
          "nextAvailable": "Tue 3/31 \u2014 5 slots (first: 8:00 AM)",
          "nextAvailableDate": "Tue 3/31",
          "source": "MyChart",
          "lastChecked": "2026-03-27T10:48:46.440044",
          "address": "14500 Hall Rd Sterling Hgts MI 48313",
          "lat": null,
          "lng": null
        },
        {
          "id": "hfpc-14932",
          "name": "Henry Ford Family Medicine - Shelby Twp North with Allison Sadowski, DO.",
          "area": "Shelby Twp",
          "type": "Primary Care",
          "sameDaySlots": 0,
          "nextDaySlots": 0,
          "nextAvailable": "Tue 3/31 \u2014 4 slots (first: 10:40 AM)",
          "nextAvailableDate": "Tue 3/31",
          "source": "MyChart",
          "lastChecked": "2026-03-27T10:48:46.440585",
          "address": "51221 Schoenherr Rd Ste 201 Shelby Twp MI 48315",
          "lat": null,
          "lng": null
        },
        {
          "id": "hfpc-80520",
          "name": "Henry Ford Medical Center - Beck Rd with Ken Smythe, MD.",
          "area": "Beck Rd Plymouth",
          "type": "Primary Care",
          "sameDaySlots": 0,
          "nextDaySlots": 0,
          "nextAvailable": "Tue 3/31 \u2014 16 slots (first: 9:20 AM)",
          "nextAvailableDate": "Tue 3/31",
          "source": "MyChart",
          "lastChecked": "2026-03-27T10:48:46.441202",
          "address": "14300 Beck Rd Plymouth MI 48170",
          "lat": 42.371,
          "lng": -83.47
        },
        {
          "id": "hfpc-46924",
          "name": "Henry Ford Family Medicine - Shelby Twp North with Angela Wilson, PA.",
          "area": "Shelby Twp",
          "type": "Primary Care",
          "sameDaySlots": 0,
          "nextDaySlots": 0,
          "nextAvailable": "Tue 3/31 \u2014 2 slots (first: 3:00 PM)",
          "nextAvailableDate": "Tue 3/31",
          "source": "MyChart",
          "lastChecked": "2026-03-27T10:48:46.441758",
          "address": "51221 Schoenherr Rd Ste 201 Shelby Twp MI 48315",
          "lat": null,
          "lng": null
        },
        {
          "id": "hfpc-38545",
          "name": "Henry Ford Medical Center - Beck Rd with Sana Zuberi, MD.",
          "area": "Beck Rd Plymouth",
          "type": "Primary Care",
          "sameDaySlots": 0,
          "nextDaySlots": 0,
          "nextAvailable": "Wed 4/1 \u2014 2 slots (first: 12:00 PM)",
          "nextAvailableDate": "Wed 4/1",
          "source": "MyChart",
          "lastChecked": "2026-03-27T10:48:46.442822",
          "address": "14300 Beck Rd Plymouth MI 48170",
          "lat": 42.371,
          "lng": -83.47
        },
        {
          "id": "hfpc-97897",
          "name": "Henry Ford Medical Center - Columbus with Wassim Chehouri, DO.",
          "area": "Mile Rd Novi",
          "type": "Primary Care",
          "sameDaySlots": 0,
          "nextDaySlots": 0,
          "nextAvailable": "Wed 4/1 \u2014 2 slots (first: 3:40 PM)",
          "nextAvailableDate": "Wed 4/1",
          "source": "MyChart",
          "lastChecked": "2026-03-27T10:48:46.443469",
          "address": "39450 W 12 Mile Rd Novi MI 48377",
          "lat": 42.48,
          "lng": -83.476
        },
        {
          "id": "hfpc-91617",
          "name": "Henry Ford Medical Center - Sterling Heights with Arifa Malik, MD.",
          "area": "Mile Rd Sterling Hgts",
          "type": "Primary Care",
          "sameDaySlots": 0,
          "nextDaySlots": 0,
          "nextAvailable": "Wed 4/1 \u2014 1 slots (first: 6:20 PM)",
          "nextAvailableDate": "Wed 4/1",
          "source": "MyChart",
          "lastChecked": "2026-03-27T10:48:46.444038",
          "address": "3500 15 Mile Rd Sterling Hgts MI 48310",
          "lat": 42.54,
          "lng": -83.05
        },
        {
          "id": "hfpc-28151",
          "name": "Henry Ford Medical Center - Columbus with Zachary Morgan, DO.",
          "area": "Mile Rd Novi",
          "type": "Primary Care",
          "sameDaySlots": 0,
          "nextDaySlots": 0,
          "nextAvailable": "Wed 4/1 \u2014 4 slots (first: 9:00 AM)",
          "nextAvailableDate": "Wed 4/1",
          "source": "MyChart",
          "lastChecked": "2026-03-27T10:48:46.444582",
          "address": "39450 W 12 Mile Rd Novi MI 48377",
          "lat": 42.48,
          "lng": -83.476
        },
        {
          "id": "hfpc-58854",
          "name": "Henry Ford Medical Center - Plymouth with Connor Olzem, DO.",
          "area": "Ann Arbor Rd Plymouth",
          "type": "Primary Care",
          "sameDaySlots": 0,
          "nextDaySlots": 0,
          "nextAvailable": "Wed 4/1 \u2014 2 slots (first: 8:40 AM)",
          "nextAvailableDate": "Wed 4/1",
          "source": "MyChart",
          "lastChecked": "2026-03-27T10:48:46.445259",
          "address": "40777 Ann Arbor Rd Plymouth MI 48170",
          "lat": 42.281,
          "lng": -83.749
        },
        {
          "id": "hfpc-10572",
          "name": "Henry Ford Medical Center - Sterling Heights with Aveena Pelia, DO.",
          "area": "Mile Rd Sterling Hgts",
          "type": "Primary Care",
          "sameDaySlots": 0,
          "nextDaySlots": 0,
          "nextAvailable": "Wed 4/1 \u2014 1 slots (first: 3:20 PM)",
          "nextAvailableDate": "Wed 4/1",
          "source": "MyChart",
          "lastChecked": "2026-03-27T10:48:46.445832",
          "address": "3500 15 Mile Rd Sterling Hgts MI 48310",
          "lat": 42.54,
          "lng": -83.05
        },
        {
          "id": "hfpc-49187",
          "name": "Henry Ford Medical Center - Brownstown with Valeria Smith, CNP.",
          "area": "Brownstown",
          "type": "Primary Care",
          "sameDaySlots": 0,
          "nextDaySlots": 0,
          "nextAvailable": "Wed 4/1 \u2014 1 slots (first: 8:20 AM)",
          "nextAvailableDate": "Wed 4/1",
          "source": "MyChart",
          "lastChecked": "2026-03-27T10:48:46.446234",
          "address": "23050 West Rd Ste 260 Brownstown MI 48183",
          "lat": 42.156,
          "lng": -83.281
        },
        {
          "id": "hfpc-26926",
          "name": "Henry Ford Medical Center - Richmond with Aco Stojanoski, CNP.",
          "area": "Main St Richmond",
          "type": "Primary Care",
          "sameDaySlots": 0,
          "nextDaySlots": 0,
          "nextAvailable": "Wed 4/1 \u2014 5 slots (first: 8:20 AM)",
          "nextAvailableDate": "Wed 4/1",
          "source": "MyChart",
          "lastChecked": "2026-03-27T10:48:46.446581",
          "address": "67267 Main St Richmond MI 48062-1919",
          "lat": null,
          "lng": null
        },
        {
          "id": "hfpc-72271",
          "name": "Henry Ford Medical Center - Woodhaven with Stephanie Workman, FNP-BC.",
          "area": "Allen Rd Woodhaven",
          "type": "Primary Care",
          "sameDaySlots": 0,
          "nextDaySlots": 0,
          "nextAvailable": "Wed 4/1 \u2014 9 slots (first: 1:20 PM)",
          "nextAvailableDate": "Wed 4/1",
          "source": "MyChart",
          "lastChecked": "2026-03-27T10:48:46.446915",
          "address": "22505 Allen Rd Woodhaven MI 48183",
          "lat": 42.139,
          "lng": -83.242
        }
      ]
    },
    "doctors_care": {
      "name": "Doctors Urgent Care",
      "locations": [
        {
          "id": "dc-65575",
          "name": "Doctors Care \u2014 Redford",
          "area": "Redford",
          "type": "Urgent Care",
          "sameDaySlots": 0,
          "nextDaySlots": 0,
          "nextAvailable": "Walk-in (no online slots)",
          "nextAvailableDate": "",
          "source": "AdvancedMD",
          "lastChecked": "2026-03-25T13:45:17.278978",
          "address": "14671 Telegraph Rd, Redford, MI 48239",
          "lat": 42.385,
          "lng": -83.297
        },
        {
          "id": "dc-10626",
          "name": "Doctors Care \u2014 Canton",
          "area": "Canton",
          "type": "Urgent Care",
          "sameDaySlots": 0,
          "nextDaySlots": 0,
          "nextAvailable": "Walk-in (no online slots)",
          "nextAvailableDate": "",
          "source": "AdvancedMD",
          "lastChecked": "2026-03-25T13:45:17.284041",
          "address": "43033 Ford Rd, Canton, MI 48187",
          "lat": 42.309,
          "lng": -83.482
        },
        {
          "id": "dc-1854",
          "name": "Doctors Care \u2014 Commerce",
          "area": "Commerce",
          "type": "Urgent Care",
          "sameDaySlots": 0,
          "nextDaySlots": 0,
          "nextAvailable": "Walk-in (no online slots)",
          "nextAvailableDate": "",
          "source": "AdvancedMD",
          "lastChecked": "2026-03-25T13:45:17.286721",
          "address": "2900 Union Lake Rd, Commerce, MI 48382",
          "lat": 42.56,
          "lng": -83.49
        },
        {
          "id": "dc-40184",
          "name": "Doctors Care \u2014 Chesterfield",
          "area": "Chesterfield",
          "type": "Urgent Care",
          "sameDaySlots": 0,
          "nextDaySlots": 0,
          "nextAvailable": "Walk-in (no online slots)",
          "nextAvailableDate": "",
          "source": "AdvancedMD",
          "lastChecked": "2026-03-25T13:45:17.289506",
          "address": "51160 Gratiot Ave, Chesterfield, MI 48051",
          "lat": 42.673,
          "lng": -82.838
        },
        {
          "id": "dc-41393",
          "name": "Doctors Care \u2014 Clinton Township",
          "area": "Clinton Township",
          "type": "Urgent Care",
          "sameDaySlots": 0,
          "nextDaySlots": 0,
          "nextAvailable": "Walk-in (no online slots)",
          "nextAvailableDate": "",
          "source": "AdvancedMD",
          "lastChecked": "2026-03-25T13:45:17.293415",
          "address": "37150 S Gratiot Ave, Clinton Township, MI 48036",
          "lat": 42.582,
          "lng": -82.929
        },
        {
          "id": "dc-37083",
          "name": "Doctors Care \u2014 Shelby",
          "area": "Shelby",
          "type": "Urgent Care",
          "sameDaySlots": 0,
          "nextDaySlots": 0,
          "nextAvailable": "Walk-in (no online slots)",
          "nextAvailableDate": "",
          "source": "AdvancedMD",
          "lastChecked": "2026-03-25T13:45:17.296593",
          "address": "46961 Van Dyke Ave, Shelby Township, MI 48317",
          "lat": 42.671,
          "lng": -83.032
        },
        {
          "id": "dc-36632",
          "name": "Doctors Care \u2014 Livonia",
          "area": "Livonia",
          "type": "Urgent Care",
          "sameDaySlots": 0,
          "nextDaySlots": 0,
          "nextAvailable": "Walk-in (no online slots)",
          "nextAvailableDate": "",
          "source": "AdvancedMD",
          "lastChecked": "2026-03-25T13:45:17.300583",
          "address": "36700 Five Mile Rd, Livonia, MI 48154",
          "lat": 42.368,
          "lng": -83.353
        },
        {
          "id": "dc-63869",
          "name": "Doctors Care \u2014 Farmington Hills",
          "area": "Farmington Hills",
          "type": "Urgent Care",
          "sameDaySlots": 0,
          "nextDaySlots": 0,
          "nextAvailable": "Walk-in (no online slots)",
          "nextAvailableDate": "",
          "source": "AdvancedMD",
          "lastChecked": "2026-03-25T13:45:17.303474",
          "address": "25950 Middlebelt Rd, Farmington Hills, MI 48336",
          "lat": 42.498,
          "lng": -83.377
        },
        {
          "id": "dc-56880",
          "name": "Doctors Care \u2014 Lambertville",
          "area": "Lambertville",
          "type": "Urgent Care",
          "sameDaySlots": 0,
          "nextDaySlots": 0,
          "nextAvailable": "Walk-in (no online slots)",
          "nextAvailableDate": "",
          "source": "AdvancedMD",
          "lastChecked": "2026-03-25T13:45:17.308392",
          "address": "3299 Sterns Rd, Lambertville, MI 48144",
          "lat": null,
          "lng": null
        },
        {
          "id": "dc-63872",
          "name": "Doctors Care \u2014 Adrian",
          "area": "Adrian",
          "type": "Urgent Care",
          "sameDaySlots": 0,
          "nextDaySlots": 0,
          "nextAvailable": "Walk-in (no online slots)",
          "nextAvailableDate": "",
          "source": "AdvancedMD",
          "lastChecked": "2026-03-25T13:45:17.316686",
          "address": "905 N Main St Suite 2, Adrian, MI 49221",
          "lat": null,
          "lng": null
        },
        {
          "id": "dc-33328",
          "name": "Doctors Care \u2014 Plainwell",
          "area": "Plainwell",
          "type": "Urgent Care",
          "sameDaySlots": 0,
          "nextDaySlots": 0,
          "nextAvailable": "Walk-in (no online slots)",
          "nextAvailableDate": "",
          "source": "AdvancedMD",
          "lastChecked": "2026-03-25T13:45:17.326343",
          "address": "1221 M-89 Suite 200, Plainwell, MI 49080",
          "lat": null,
          "lng": null
        },
        {
          "id": "dc-16805",
          "name": "Doctors Care \u2014 Rochester Hills",
          "area": "Rochester Hills",
          "type": "Urgent Care",
          "sameDaySlots": 0,
          "nextDaySlots": 0,
          "nextAvailable": "Walk-in (no online slots)",
          "nextAvailableDate": "",
          "source": "AdvancedMD",
          "lastChecked": "2026-03-25T13:45:17.336147",
          "address": "2915 Walton Blvd, Rochester Hills, MI 48309",
          "lat": 42.65,
          "lng": -83.15
        },
        {
          "id": "dc-38190",
          "name": "Doctors Care \u2014 Taylor",
          "area": "Taylor",
          "type": "Urgent Care",
          "sameDaySlots": 0,
          "nextDaySlots": 0,
          "nextAvailable": "Walk-in (no online slots)",
          "nextAvailableDate": "",
          "source": "AdvancedMD",
          "lastChecked": "2026-03-25T13:45:17.345000",
          "address": "23234 Ecorse Rd, Taylor, MI 48180",
          "lat": 42.241,
          "lng": -83.269
        },
        {
          "id": "dc-68985",
          "name": "Doctors Care \u2014 Troy",
          "area": "Troy",
          "type": "Urgent Care",
          "sameDaySlots": 0,
          "nextDaySlots": 0,
          "nextAvailable": "Walk-in (no online slots)",
          "nextAvailableDate": "",
          "source": "AdvancedMD",
          "lastChecked": "2026-03-25T13:45:17.352460",
          "address": "4060 Rochester Rd, Troy, MI 48085",
          "lat": 42.6,
          "lng": -83.12
        },
        {
          "id": "dc-89184",
          "name": "Doctors Care \u2014 Tecumseh",
          "area": "Tecumseh",
          "type": "Urgent Care",
          "sameDaySlots": 0,
          "nextDaySlots": 0,
          "nextAvailable": "Walk-in (no online slots)",
          "nextAvailableDate": "",
          "source": "AdvancedMD",
          "lastChecked": "2026-03-25T13:45:17.359718",
          "address": "501 E Chicago Blvd, Tecumseh, MI 49286",
          "lat": null,
          "lng": null
        },
        {
          "id": "dc-68621",
          "name": "Doctors Care \u2014 Ypsilanti",
          "area": "Ypsilanti",
          "type": "Urgent Care",
          "sameDaySlots": 0,
          "nextDaySlots": 0,
          "nextAvailable": "Walk-in (no online slots)",
          "nextAvailableDate": "",
          "source": "AdvancedMD",
          "lastChecked": "2026-03-25T13:45:17.367202",
          "address": "301 W Michigan Ave Ste 100, Ypsilanti, MI 48197",
          "lat": 42.22,
          "lng": -83.62
        }
      ]
    }
  },
  "errors": []
}